{
"meta":{"test_sets":[],"test_metrics":[],"learn_metrics":[{"best_value":"Min","name":"RMSE"}],"launch_mode":"Train","parameters":"","iteration_count":1000,"learn_sets":["learn"],"name":"experiment"},
"iterations":[
{"learn":[14.59871775],"iteration":0,"passed_time":0.1457305466,"remaining_time":145.584816},
{"learn":[14.22518863],"iteration":1,"passed_time":0.1468604571,"remaining_time":73.28336807},
{"learn":[13.8866124],"iteration":2,"passed_time":0.1479501934,"remaining_time":49.16878095},
{"learn":[13.52356875],"iteration":3,"passed_time":0.1489161447,"remaining_time":37.08012002},
{"learn":[13.18870211],"iteration":4,"passed_time":0.150092383,"remaining_time":29.86838422},
{"learn":[12.9124226],"iteration":5,"passed_time":0.1512032629,"remaining_time":25.04934055},
{"learn":[12.60003351],"iteration":6,"passed_time":0.1522494319,"remaining_time":21.59766941},
{"learn":[12.32990573],"iteration":7,"passed_time":0.1531913742,"remaining_time":18.9957304},
{"learn":[12.0660619],"iteration":8,"passed_time":0.154168645,"remaining_time":16.9756808},
{"learn":[11.77309809],"iteration":9,"passed_time":0.1552231975,"remaining_time":15.36709655},
{"learn":[11.49227636],"iteration":10,"passed_time":0.156300501,"remaining_time":14.05283596},
{"learn":[11.26264833],"iteration":11,"passed_time":0.1572584218,"remaining_time":12.94761006},
{"learn":[11.04260393],"iteration":12,"passed_time":0.158357827,"remaining_time":12.02301348},
{"learn":[10.79916926],"iteration":13,"passed_time":0.1593074414,"remaining_time":11.21979552},
{"learn":[10.5541002],"iteration":14,"passed_time":0.1604200213,"remaining_time":10.53424807},
{"learn":[10.31918115],"iteration":15,"passed_time":0.1616102314,"remaining_time":9.939029228},
{"learn":[10.10004441],"iteration":16,"passed_time":0.1626431351,"remaining_time":9.404600104},
{"learn":[9.894556723],"iteration":17,"passed_time":0.1636160664,"remaining_time":8.926165398},
{"learn":[9.690174082],"iteration":18,"passed_time":0.1648505188,"remaining_time":8.511492575},
{"learn":[9.506034866],"iteration":19,"passed_time":0.165856594,"remaining_time":8.126973105},
{"learn":[9.338524633],"iteration":20,"passed_time":0.1669251772,"remaining_time":7.781892786},
{"learn":[9.170203312],"iteration":21,"passed_time":0.1680980953,"remaining_time":7.472724418},
{"learn":[9.010299969],"iteration":22,"passed_time":0.1695748542,"remaining_time":7.203244895},
{"learn":[8.843866678],"iteration":23,"passed_time":0.1707722357,"remaining_time":6.944737583},
{"learn":[8.690548059],"iteration":24,"passed_time":0.1719215768,"remaining_time":6.704941496},
{"learn":[8.555307687],"iteration":25,"passed_time":0.1730462594,"remaining_time":6.482579102},
{"learn":[8.413851302],"iteration":26,"passed_time":0.17410029,"remaining_time":6.274058599},
{"learn":[8.29256019],"iteration":27,"passed_time":0.1751301072,"remaining_time":6.079516578},
{"learn":[8.162193833],"iteration":28,"passed_time":0.1762078663,"remaining_time":5.899925454},
{"learn":[8.040736294],"iteration":29,"passed_time":0.1771599072,"remaining_time":5.728170331},
{"learn":[7.921220278],"iteration":30,"passed_time":0.1781671643,"remaining_time":5.569160718},
{"learn":[7.809589039],"iteration":31,"passed_time":0.1791218836,"remaining_time":5.418436979},
{"learn":[7.699675801],"iteration":32,"passed_time":0.1802055955,"remaining_time":5.280570024},
{"learn":[7.60645267],"iteration":33,"passed_time":0.1812308371,"remaining_time":5.1490879},
{"learn":[7.498880302],"iteration":34,"passed_time":0.182205926,"remaining_time":5.023677673},
{"learn":[7.401158744],"iteration":35,"passed_time":0.1831742462,"remaining_time":4.904999259},
{"learn":[7.306431077],"iteration":36,"passed_time":0.1842655569,"remaining_time":4.795884629},
{"learn":[7.223863468],"iteration":37,"passed_time":0.1853528429,"remaining_time":4.692353548},
{"learn":[7.143477682],"iteration":38,"passed_time":0.1865030697,"remaining_time":4.595626923},
{"learn":[7.062817131],"iteration":39,"passed_time":0.1875020094,"remaining_time":4.500048226},
{"learn":[6.990793435],"iteration":40,"passed_time":0.1885028659,"remaining_time":4.409128011},
{"learn":[6.931862224],"iteration":41,"passed_time":0.1895194679,"remaining_time":4.322848816},
{"learn":[6.858296558],"iteration":42,"passed_time":0.19056523,"remaining_time":4.241184305},
{"learn":[6.786268161],"iteration":43,"passed_time":0.1915428356,"remaining_time":4.161703429},
{"learn":[6.717118549],"iteration":44,"passed_time":0.1924991724,"remaining_time":4.085260214},
{"learn":[6.652948106],"iteration":45,"passed_time":0.193536615,"remaining_time":4.013781103},
{"learn":[6.589686076],"iteration":46,"passed_time":0.1944783629,"remaining_time":3.943359146},
{"learn":[6.531283097],"iteration":47,"passed_time":0.1954868221,"remaining_time":3.877155306},
{"learn":[6.471368031],"iteration":48,"passed_time":0.1964788817,"remaining_time":3.813294213},
{"learn":[6.416481395],"iteration":49,"passed_time":0.1976795915,"remaining_time":3.755912238},
{"learn":[6.369870822],"iteration":50,"passed_time":0.1989576166,"remaining_time":3.702172121},
{"learn":[6.325678067],"iteration":51,"passed_time":0.199932704,"remaining_time":3.644926988},
{"learn":[6.275766122],"iteration":52,"passed_time":0.2011190409,"remaining_time":3.593579844},
{"learn":[6.224773967],"iteration":53,"passed_time":0.2021824086,"remaining_time":3.541936269},
{"learn":[6.182249254],"iteration":54,"passed_time":0.2033028894,"remaining_time":3.493113282},
{"learn":[6.139904173],"iteration":55,"passed_time":0.2043257393,"remaining_time":3.444348176},
{"learn":[6.100525536],"iteration":56,"passed_time":0.2052847209,"remaining_time":3.39620161},
{"learn":[6.062568564],"iteration":57,"passed_time":0.2064595427,"remaining_time":3.353187745},
{"learn":[6.030559288],"iteration":58,"passed_time":0.207539766,"remaining_time":3.310083387},
{"learn":[5.997931376],"iteration":59,"passed_time":0.2085761278,"remaining_time":3.267692668},
{"learn":[5.964103835],"iteration":60,"passed_time":0.2095840261,"remaining_time":3.22621968},
{"learn":[5.933729724],"iteration":61,"passed_time":0.2105639849,"remaining_time":3.18562932},
{"learn":[5.901932711],"iteration":62,"passed_time":0.2116481176,"remaining_time":3.147845813},
{"learn":[5.873727795],"iteration":63,"passed_time":0.2130154018,"remaining_time":3.115350251},
{"learn":[5.846485734],"iteration":64,"passed_time":0.2141540198,"remaining_time":3.080523208},
{"learn":[5.820630862],"iteration":65,"passed_time":0.2151371342,"remaining_time":3.044516414},
{"learn":[5.793646238],"iteration":66,"passed_time":0.2162733064,"remaining_time":3.011686491},
{"learn":[5.765388646],"iteration":67,"passed_time":0.2173876863,"remaining_time":2.979490054},
{"learn":[5.747073912],"iteration":68,"passed_time":0.218632394,"remaining_time":2.949953026},
{"learn":[5.722315217],"iteration":69,"passed_time":0.2197142499,"remaining_time":2.919060749},
{"learn":[5.699970599],"iteration":70,"passed_time":0.2207178921,"remaining_time":2.887984814},
{"learn":[5.682732647],"iteration":71,"passed_time":0.2217981706,"remaining_time":2.858731977},
{"learn":[5.663525791],"iteration":72,"passed_time":0.2228528829,"remaining_time":2.829926335},
{"learn":[5.642381613],"iteration":73,"passed_time":0.2238253254,"remaining_time":2.800841234},
{"learn":[5.621404779],"iteration":74,"passed_time":0.2248737948,"remaining_time":2.773443469},
{"learn":[5.602460129],"iteration":75,"passed_time":0.2259925138,"remaining_time":2.747593194},
{"learn":[5.587337574],"iteration":76,"passed_time":0.2270979081,"remaining_time":2.722225573},
{"learn":[5.572393026],"iteration":77,"passed_time":0.228166533,"remaining_time":2.697045428},
{"learn":[5.558425806],"iteration":78,"passed_time":0.2293760641,"remaining_time":2.674118419},
{"learn":[5.541518902],"iteration":79,"passed_time":0.2304582588,"remaining_time":2.650269976},
{"learn":[5.526157283],"iteration":80,"passed_time":0.2315290378,"remaining_time":2.626854145},
{"learn":[5.511746977],"iteration":81,"passed_time":0.2325424649,"remaining_time":2.603341254},
{"learn":[5.504975022],"iteration":82,"passed_time":0.2330509908,"remaining_time":2.574792272},
{"learn":[5.493980522],"iteration":83,"passed_time":0.2341780524,"remaining_time":2.553655905},
{"learn":[5.480745463],"iteration":84,"passed_time":0.2352988716,"remaining_time":2.532923147},
{"learn":[5.464052013],"iteration":85,"passed_time":0.2362820125,"remaining_time":2.51118325},
{"learn":[5.449143727],"iteration":86,"passed_time":0.237276502,"remaining_time":2.490039613},
{"learn":[5.438255432],"iteration":87,"passed_time":0.2383718648,"remaining_time":2.470399326},
{"learn":[5.425927931],"iteration":88,"passed_time":0.2394745398,"remaining_time":2.451250626},
{"learn":[5.412331217],"iteration":89,"passed_time":0.2405518001,"remaining_time":2.432245979},
{"learn":[5.400691499],"iteration":90,"passed_time":0.2427078711,"remaining_time":2.424411591},
{"learn":[5.391618744],"iteration":91,"passed_time":0.2438720835,"remaining_time":2.406911433},
{"learn":[5.380766572],"iteration":92,"passed_time":0.2448709781,"remaining_time":2.388150291},
{"learn":[5.372207183],"iteration":93,"passed_time":0.2458388979,"remaining_time":2.369468526},
{"learn":[5.362918837],"iteration":94,"passed_time":0.246913925,"remaining_time":2.352180022},
{"learn":[5.348292324],"iteration":95,"passed_time":0.2480510909,"remaining_time":2.33581444},
{"learn":[5.339772295],"iteration":96,"passed_time":0.2490268715,"remaining_time":2.318260464},
{"learn":[5.331515983],"iteration":97,"passed_time":0.2500525251,"remaining_time":2.301503854},
{"learn":[5.323861644],"iteration":98,"passed_time":0.2509867235,"remaining_time":2.284232706},
{"learn":[5.313277281],"iteration":99,"passed_time":0.2520332417,"remaining_time":2.268299175},
{"learn":[5.30685627],"iteration":100,"passed_time":0.2530112964,"remaining_time":2.252051044},
{"learn":[5.29652059],"iteration":101,"passed_time":0.254069629,"remaining_time":2.236809087},
{"learn":[5.288350766],"iteration":102,"passed_time":0.2551106836,"remaining_time":2.22169207},
{"learn":[5.27993346],"iteration":103,"passed_time":0.256193198,"remaining_time":2.207202937},
{"learn":[5.271789139],"iteration":104,"passed_time":0.2574265449,"remaining_time":2.194254835},
{"learn":[5.262684686],"iteration":105,"passed_time":0.2584881658,"remaining_time":2.180079436},
{"learn":[5.251619772],"iteration":106,"passed_time":0.2595847056,"remaining_time":2.16644058},
{"learn":[5.241012171],"iteration":107,"passed_time":0.2607387211,"remaining_time":2.153508696},
{"learn":[5.232684032],"iteration":108,"passed_time":0.261846482,"remaining_time":2.140414821},
{"learn":[5.224267141],"iteration":109,"passed_time":0.2628203611,"remaining_time":2.126455649},
{"learn":[5.216324968],"iteration":110,"passed_time":0.2639070796,"remaining_time":2.113634178},
{"learn":[5.211102527],"iteration":111,"passed_time":0.2650142303,"remaining_time":2.101184254},
{"learn":[5.206364257],"iteration":112,"passed_time":0.2661542675,"remaining_time":2.089193233},
{"learn":[5.196937641],"iteration":113,"passed_time":0.267292467,"remaining_time":2.077378296},
{"learn":[5.190746047],"iteration":114,"passed_time":0.2684909228,"remaining_time":2.066212753},
{"learn":[5.181885213],"iteration":115,"passed_time":0.2696411454,"remaining_time":2.054851487},
{"learn":[5.178293568],"iteration":116,"passed_time":0.2707854627,"remaining_time":2.043620201},
{"learn":[5.170991438],"iteration":117,"passed_time":0.2721507972,"remaining_time":2.034211891},
{"learn":[5.166257212],"iteration":118,"passed_time":0.2734662757,"remaining_time":2.024569654},
{"learn":[5.161421246],"iteration":119,"passed_time":0.2745509091,"remaining_time":2.013373334},
{"learn":[5.158223542],"iteration":120,"passed_time":0.2756725283,"remaining_time":2.00261283},
{"learn":[5.15470988],"iteration":121,"passed_time":0.2765648649,"remaining_time":1.990360257},
{"learn":[5.146388143],"iteration":122,"passed_time":0.277701595,"remaining_time":1.98003495},
{"learn":[5.139529364],"iteration":123,"passed_time":0.278821457,"remaining_time":1.96973868},
{"learn":[5.134276023],"iteration":124,"passed_time":0.2799757333,"remaining_time":1.959830133},
{"learn":[5.128536065],"iteration":125,"passed_time":0.2810152313,"remaining_time":1.949264382},
{"learn":[5.123300353],"iteration":126,"passed_time":0.2818574745,"remaining_time":1.937492719},
{"learn":[5.116200518],"iteration":127,"passed_time":0.2829306804,"remaining_time":1.92746526},
{"learn":[5.108728704],"iteration":128,"passed_time":0.2840897471,"remaining_time":1.918156355},
{"learn":[5.104075866],"iteration":129,"passed_time":0.2853151121,"remaining_time":1.909416519},
{"learn":[5.100317606],"iteration":130,"passed_time":0.2865088835,"remaining_time":1.90058183},
{"learn":[5.095814182],"iteration":131,"passed_time":0.2876183765,"remaining_time":1.891308718},
{"learn":[5.092146915],"iteration":132,"passed_time":0.2887737206,"remaining_time":1.882457261},
{"learn":[5.085258329],"iteration":133,"passed_time":0.289853682,"remaining_time":1.873233497},
{"learn":[5.079219421],"iteration":134,"passed_time":0.2909319048,"remaining_time":1.864119242},
{"learn":[5.076476829],"iteration":135,"passed_time":0.2921297399,"remaining_time":1.855883054},
{"learn":[5.072133867],"iteration":136,"passed_time":0.2931553056,"remaining_time":1.846664443},
{"learn":[5.067031564],"iteration":137,"passed_time":0.2942759037,"remaining_time":1.838158181},
{"learn":[5.061358312],"iteration":138,"passed_time":0.2955327491,"remaining_time":1.830602136},
{"learn":[5.056759124],"iteration":139,"passed_time":0.2965267467,"remaining_time":1.821521444},
{"learn":[5.050254],"iteration":140,"passed_time":0.2976250849,"remaining_time":1.81319112},
{"learn":[5.048376474],"iteration":141,"passed_time":0.2984022077,"remaining_time":1.80302179},
{"learn":[5.042603751],"iteration":142,"passed_time":0.2995126971,"remaining_time":1.794981688},
{"learn":[5.037477349],"iteration":143,"passed_time":0.3005966231,"remaining_time":1.786879926},
{"learn":[5.03230489],"iteration":144,"passed_time":0.3019174995,"remaining_time":1.780272153},
{"learn":[5.025976187],"iteration":145,"passed_time":0.3029076349,"remaining_time":1.771802193},
{"learn":[5.01952451],"iteration":146,"passed_time":0.3038692312,"remaining_time":1.763268396},
{"learn":[5.017569424],"iteration":147,"passed_time":0.3048178052,"remaining_time":1.75476196},
{"learn":[5.008962367],"iteration":148,"passed_time":0.3059283328,"remaining_time":1.747281955},
{"learn":[5.003880266],"iteration":149,"passed_time":0.3069655556,"remaining_time":1.739471482},
{"learn":[4.996387564],"iteration":150,"passed_time":0.3080262993,"remaining_time":1.731882967},
{"learn":[4.993361683],"iteration":151,"passed_time":0.3089388701,"remaining_time":1.723553696},
{"learn":[4.99005752],"iteration":152,"passed_time":0.3099081686,"remaining_time":1.715635417},
{"learn":[4.986908764],"iteration":153,"passed_time":0.3109330441,"remaining_time":1.708112697},
{"learn":[4.985207175],"iteration":154,"passed_time":0.312027321,"remaining_time":1.701052169},
{"learn":[4.979003494],"iteration":155,"passed_time":0.3131338529,"remaining_time":1.694134435},
{"learn":[4.973142217],"iteration":156,"passed_time":0.3142187479,"remaining_time":1.687174551},
{"learn":[4.967056696],"iteration":157,"passed_time":0.3153692097,"remaining_time":1.680638446},
{"learn":[4.961460696],"iteration":158,"passed_time":0.3166623677,"remaining_time":1.67492485},
{"learn":[4.954240363],"iteration":159,"passed_time":0.3178176743,"remaining_time":1.66854279},
{"learn":[4.952320707],"iteration":160,"passed_time":0.3186365852,"remaining_time":1.66047264},
{"learn":[4.948337777],"iteration":161,"passed_time":0.3197333156,"remaining_time":1.653929126},
{"learn":[4.943228639],"iteration":162,"passed_time":0.3209471152,"remaining_time":1.648053592},
{"learn":[4.938545759],"iteration":163,"passed_time":0.3221429632,"remaining_time":1.642143398},
{"learn":[4.935330572],"iteration":164,"passed_time":0.3232144725,"remaining_time":1.635661119},
{"learn":[4.932051543],"iteration":165,"passed_time":0.324343819,"remaining_time":1.629534609},
{"learn":[4.928964153],"iteration":166,"passed_time":0.325491469,"remaining_time":1.623559243},
{"learn":[4.922860227],"iteration":167,"passed_time":0.3267962281,"remaining_time":1.618419416},
{"learn":[4.917668772],"iteration":168,"passed_time":0.3279660404,"remaining_time":1.612661417},
{"learn":[4.910365386],"iteration":169,"passed_time":0.3290364356,"remaining_time":1.606472009},
{"learn":[4.906457206],"iteration":170,"passed_time":0.3300569955,"remaining_time":1.600100873},
{"learn":[4.901996508],"iteration":171,"passed_time":0.331326251,"remaining_time":1.594989162},
{"learn":[4.896816173],"iteration":172,"passed_time":0.3324651071,"remaining_time":1.589298518},
{"learn":[4.891123132],"iteration":173,"passed_time":0.3335934934,"remaining_time":1.583610492},
{"learn":[4.887630202],"iteration":174,"passed_time":0.3347096829,"remaining_time":1.577917077},
{"learn":[4.885259712],"iteration":175,"passed_time":0.3358718956,"remaining_time":1.572491147},
{"learn":[4.880659728],"iteration":176,"passed_time":0.3368804694,"remaining_time":1.566399019},
{"learn":[4.877299723],"iteration":177,"passed_time":0.3379454017,"remaining_time":1.560624271},
{"learn":[4.874038772],"iteration":178,"passed_time":0.3390377617,"remaining_time":1.555027946},
{"learn":[4.86943698],"iteration":179,"passed_time":0.3401098821,"remaining_time":1.549389463},
{"learn":[4.861268711],"iteration":180,"passed_time":0.3412780282,"remaining_time":1.54423594},
{"learn":[4.858673056],"iteration":181,"passed_time":0.3424704209,"remaining_time":1.539235188},
{"learn":[4.854036207],"iteration":182,"passed_time":0.34360786,"remaining_time":1.534030719},
{"learn":[4.85130244],"iteration":183,"passed_time":0.3448947184,"remaining_time":1.529533099},
{"learn":[4.847510084],"iteration":184,"passed_time":0.3459394436,"remaining_time":1.524003495},
{"learn":[4.845691673],"iteration":185,"passed_time":0.3471148942,"remaining_time":1.519094214},
{"learn":[4.842058646],"iteration":186,"passed_time":0.3483103969,"remaining_time":1.514312046},
{"learn":[4.838623675],"iteration":187,"passed_time":0.3492975962,"remaining_time":1.508668341},
{"learn":[4.834602161],"iteration":188,"passed_time":0.3504863565,"remaining_time":1.50393881},
{"learn":[4.830858976],"iteration":189,"passed_time":0.3515570773,"remaining_time":1.498743329},
{"learn":[4.827590511],"iteration":190,"passed_time":0.3526644108,"remaining_time":1.493746117},
{"learn":[4.822246226],"iteration":191,"passed_time":0.3537789122,"remaining_time":1.488819589},
{"learn":[4.816686395],"iteration":192,"passed_time":0.3548755526,"remaining_time":1.483857881},
{"learn":[4.814797121],"iteration":193,"passed_time":0.3560072334,"remaining_time":1.479081599},
{"learn":[4.811639392],"iteration":194,"passed_time":0.3572440267,"remaining_time":1.474776623},
{"learn":[4.804813432],"iteration":195,"passed_time":0.3583682332,"remaining_time":1.47004112},
{"learn":[4.80251613],"iteration":196,"passed_time":0.3595508961,"remaining_time":1.465580556},
{"learn":[4.800087884],"iteration":197,"passed_time":0.3607775306,"remaining_time":1.46133121},
{"learn":[4.794773135],"iteration":198,"passed_time":0.3620415358,"remaining_time":1.457262664},
{"learn":[4.791664833],"iteration":199,"passed_time":0.3632588043,"remaining_time":1.453035217},
{"learn":[4.785989873],"iteration":200,"passed_time":0.3644659695,"remaining_time":1.448797561},
{"learn":[4.782387142],"iteration":201,"passed_time":0.365663415,"remaining_time":1.444551511},
{"learn":[4.778623704],"iteration":202,"passed_time":0.3668331192,"remaining_time":1.440226581},
{"learn":[4.775772178],"iteration":203,"passed_time":0.3679924568,"remaining_time":1.435892135},
{"learn":[4.77023101],"iteration":204,"passed_time":0.3691011894,"remaining_time":1.431392418},
{"learn":[4.764496689],"iteration":205,"passed_time":0.3704068397,"remaining_time":1.427684615},
{"learn":[4.763138716],"iteration":206,"passed_time":0.3715487229,"remaining_time":1.423372644},
{"learn":[4.758053283],"iteration":207,"passed_time":0.3726453834,"remaining_time":1.41891896},
{"learn":[4.755063788],"iteration":208,"passed_time":0.3738470607,"remaining_time":1.414894856},
{"learn":[4.752465267],"iteration":209,"passed_time":0.376185926,"remaining_time":1.415175626},
{"learn":[4.748067377],"iteration":210,"passed_time":0.3775811563,"remaining_time":1.411902997},
{"learn":[4.744163298],"iteration":211,"passed_time":0.3789273294,"remaining_time":1.408465734},
{"learn":[4.736670896],"iteration":212,"passed_time":0.3801240758,"remaining_time":1.404495998},
{"learn":[4.73349255],"iteration":213,"passed_time":0.3812774023,"remaining_time":1.400392702},
{"learn":[4.731864595],"iteration":214,"passed_time":0.3825138527,"remaining_time":1.396620346},
{"learn":[4.728398311],"iteration":215,"passed_time":0.3838150886,"remaining_time":1.393106618},
{"learn":[4.723865975],"iteration":216,"passed_time":0.3850691253,"remaining_time":1.389442973},
{"learn":[4.723483365],"iteration":217,"passed_time":0.386269859,"remaining_time":1.385610228},
{"learn":[4.72095416],"iteration":218,"passed_time":0.3874400099,"remaining_time":1.381692456},
{"learn":[4.716173382],"iteration":219,"passed_time":0.3887365044,"remaining_time":1.378247607},
{"learn":[4.710563974],"iteration":220,"passed_time":0.390030427,"remaining_time":1.374813134},
{"learn":[4.707160263],"iteration":221,"passed_time":0.3915011773,"remaining_time":1.372017639},
{"learn":[4.70408351],"iteration":222,"passed_time":0.3938562656,"remaining_time":1.372315329},
{"learn":[4.702501831],"iteration":223,"passed_time":0.395849773,"remaining_time":1.371336714},
{"learn":[4.700269738],"iteration":224,"passed_time":0.3976548347,"remaining_time":1.369699986},
{"learn":[4.695346302],"iteration":225,"passed_time":0.3992642414,"remaining_time":1.367391694},
{"learn":[4.689769299],"iteration":226,"passed_time":0.4010665012,"remaining_time":1.36574628},
{"learn":[4.687919514],"iteration":227,"passed_time":0.4042913989,"remaining_time":1.368916491},
{"learn":[4.682982074],"iteration":228,"passed_time":0.4057396416,"remaining_time":1.366049186},
{"learn":[4.679578702],"iteration":229,"passed_time":0.4072267665,"remaining_time":1.363324392},
{"learn":[4.675751423],"iteration":230,"passed_time":0.4086237489,"remaining_time":1.360310229},
{"learn":[4.672710726],"iteration":231,"passed_time":0.4102303908,"remaining_time":1.358004052},
{"learn":[4.6690533],"iteration":232,"passed_time":0.4123309534,"remaining_time":1.357329791},
{"learn":[4.667595702],"iteration":233,"passed_time":0.4137427694,"remaining_time":1.354388724},
{"learn":[4.664241291],"iteration":234,"passed_time":0.4150609543,"remaining_time":1.351155873},
{"learn":[4.662246999],"iteration":235,"passed_time":0.4165609279,"remaining_time":1.34852775},
{"learn":[4.658668443],"iteration":236,"passed_time":0.4183044228,"remaining_time":1.346693142},
{"learn":[4.658017572],"iteration":237,"passed_time":0.4199461089,"remaining_time":1.34453334},
{"learn":[4.657656705],"iteration":238,"passed_time":0.4212928811,"remaining_time":1.341438839},
{"learn":[4.653242871],"iteration":239,"passed_time":0.4225282416,"remaining_time":1.338006099},
{"learn":[4.6507302],"iteration":240,"passed_time":0.4237740819,"remaining_time":1.334624598},
{"learn":[4.647671336],"iteration":241,"passed_time":0.4250377099,"remaining_time":1.331316463},
{"learn":[4.645506007],"iteration":242,"passed_time":0.4262980067,"remaining_time":1.328014778},
{"learn":[4.641297906],"iteration":243,"passed_time":0.4274831061,"remaining_time":1.324496837},
{"learn":[4.63798107],"iteration":244,"passed_time":0.4286544499,"remaining_time":1.32095555},
{"learn":[4.635062318],"iteration":245,"passed_time":0.4299573539,"remaining_time":1.317836768},
{"learn":[4.631606017],"iteration":246,"passed_time":0.4313002638,"remaining_time":1.31485465},
{"learn":[4.630215494],"iteration":247,"passed_time":0.4328987039,"remaining_time":1.312660586},
{"learn":[4.62729814],"iteration":248,"passed_time":0.4347064941,"remaining_time":1.311102719},
{"learn":[4.624691756],"iteration":249,"passed_time":0.436315498,"remaining_time":1.308946494},
{"learn":[4.621840053],"iteration":250,"passed_time":0.4375220437,"remaining_time":1.305593668},
{"learn":[4.619602091],"iteration":251,"passed_time":0.4388013735,"remaining_time":1.302473918},
{"learn":[4.613584029],"iteration":252,"passed_time":0.4399365922,"remaining_time":1.298943219},
{"learn":[4.6119388],"iteration":253,"passed_time":0.4410223362,"remaining_time":1.295286074},
{"learn":[4.60870702],"iteration":254,"passed_time":0.4421182626,"remaining_time":1.291678846},
{"learn":[4.604771557],"iteration":255,"passed_time":0.4431878643,"remaining_time":1.288014731},
{"learn":[4.604231277],"iteration":256,"passed_time":0.4442996584,"remaining_time":1.284492787},
{"learn":[4.600750354],"iteration":257,"passed_time":0.4454295303,"remaining_time":1.281041517},
{"learn":[4.596488253],"iteration":258,"passed_time":0.4465482601,"remaining_time":1.277576296},
{"learn":[4.59470784],"iteration":259,"passed_time":0.4476373029,"remaining_time":1.274044631},
{"learn":[4.588818005],"iteration":260,"passed_time":0.4486865832,"remaining_time":1.2704191},
{"learn":[4.585054174],"iteration":261,"passed_time":0.4498365107,"remaining_time":1.267096736},
{"learn":[4.581471435],"iteration":262,"passed_time":0.4510149911,"remaining_time":1.263870907},
{"learn":[4.577555199],"iteration":263,"passed_time":0.4522446099,"remaining_time":1.260803155},
{"learn":[4.57457145],"iteration":264,"passed_time":0.4534551799,"remaining_time":1.257696442},
{"learn":[4.573029224],"iteration":265,"passed_time":0.45455929,"remaining_time":1.254310221},
{"learn":[4.571326203],"iteration":266,"passed_time":0.4557729831,"remaining_time":1.251241935},
{"learn":[4.571019224],"iteration":267,"passed_time":0.4569275831,"remaining_time":1.248026085},
{"learn":[4.565766631],"iteration":268,"passed_time":0.458112765,"remaining_time":1.244908666},
{"learn":[4.563383471],"iteration":269,"passed_time":0.4593013379,"remaining_time":1.241814728},
{"learn":[4.558165805],"iteration":270,"passed_time":0.4605275036,"remaining_time":1.238835978},
{"learn":[4.55629209],"iteration":271,"passed_time":0.4617471816,"remaining_time":1.235852751},
{"learn":[4.549383848],"iteration":272,"passed_time":0.4631164062,"remaining_time":1.233280686},
{"learn":[4.546227503],"iteration":273,"passed_time":0.4644834983,"remaining_time":1.230711751},
{"learn":[4.540620977],"iteration":274,"passed_time":0.4657618185,"remaining_time":1.227917522},
{"learn":[4.532898237],"iteration":275,"passed_time":0.4669117839,"remaining_time":1.224797578},
{"learn":[4.529757367],"iteration":276,"passed_time":0.4681939475,"remaining_time":1.22203691},
{"learn":[4.52579294],"iteration":277,"passed_time":0.4694342574,"remaining_time":1.219178179},
{"learn":[4.521572155],"iteration":278,"passed_time":0.4706211942,"remaining_time":1.216193122},
{"learn":[4.518818099],"iteration":279,"passed_time":0.4717430727,"remaining_time":1.213053615},
{"learn":[4.514012334],"iteration":280,"passed_time":0.4728574449,"remaining_time":1.209909263},
{"learn":[4.508331416],"iteration":281,"passed_time":0.4740377866,"remaining_time":1.206947272},
{"learn":[4.506038537],"iteration":282,"passed_time":0.4751218156,"remaining_time":1.203753858},
{"learn":[4.505805643],"iteration":283,"passed_time":0.4761257714,"remaining_time":1.200373424},
{"learn":[4.501550352],"iteration":284,"passed_time":0.4773246546,"remaining_time":1.197498695},
{"learn":[4.494692643],"iteration":285,"passed_time":0.4784874154,"remaining_time":1.194545506},
{"learn":[4.489330245],"iteration":286,"passed_time":0.4795798761,"remaining_time":1.191430145},
{"learn":[4.484826955],"iteration":287,"passed_time":0.4807919814,"remaining_time":1.188624621},
{"learn":[4.478285428],"iteration":288,"passed_time":0.4818860882,"remaining_time":1.185539822},
{"learn":[4.475311671],"iteration":289,"passed_time":0.4829632539,"remaining_time":1.182427277},
{"learn":[4.471581298],"iteration":290,"passed_time":0.4841317141,"remaining_time":1.179551152},
{"learn":[4.469164956],"iteration":291,"passed_time":0.4852297398,"remaining_time":1.176515944},
{"learn":[4.462068024],"iteration":292,"passed_time":0.4863579992,"remaining_time":1.173566913},
{"learn":[4.458540976],"iteration":293,"passed_time":0.4875654677,"remaining_time":1.170820477},
{"learn":[4.455757458],"iteration":294,"passed_time":0.4888665373,"remaining_time":1.168308166},
{"learn":[4.453027414],"iteration":295,"passed_time":0.4900062243,"remaining_time":1.165420209},
{"learn":[4.450659338],"iteration":296,"passed_time":0.4914228519,"remaining_time":1.163199545},
{"learn":[4.444696901],"iteration":297,"passed_time":0.4930756156,"remaining_time":1.161540544},
{"learn":[4.442052813],"iteration":298,"passed_time":0.4945417818,"remaining_time":1.159444111},
{"learn":[4.440036756],"iteration":299,"passed_time":0.4959334989,"remaining_time":1.157178164},
{"learn":[4.435017051],"iteration":300,"passed_time":0.4970523078,"remaining_time":1.154284263},
{"learn":[4.429962125],"iteration":301,"passed_time":0.4983631393,"remaining_time":1.151845931},
{"learn":[4.427666256],"iteration":302,"passed_time":0.4997069755,"remaining_time":1.149490963},
{"learn":[4.425030004],"iteration":303,"passed_time":0.5011005971,"remaining_time":1.14725663},
{"learn":[4.422588771],"iteration":304,"passed_time":0.5024267061,"remaining_time":1.14487397},
{"learn":[4.418936667],"iteration":305,"passed_time":0.5036502672,"remaining_time":1.142265639},
{"learn":[4.416887976],"iteration":306,"passed_time":0.5048860417,"remaining_time":1.139693899},
{"learn":[4.413773354],"iteration":307,"passed_time":0.5061573333,"remaining_time":1.137210632},
{"learn":[4.411129391],"iteration":308,"passed_time":0.5075993026,"remaining_time":1.135116887},
{"learn":[4.40850819],"iteration":309,"passed_time":0.5089732147,"remaining_time":1.132875865},
{"learn":[4.404880292],"iteration":310,"passed_time":0.5101761885,"remaining_time":1.130261717},
{"learn":[4.404593827],"iteration":311,"passed_time":0.511409344,"remaining_time":1.127723169},
{"learn":[4.402139942],"iteration":312,"passed_time":0.5126443882,"remaining_time":1.125197108},
{"learn":[4.400284725],"iteration":313,"passed_time":0.5138139235,"remaining_time":1.122536151},
{"learn":[4.395805521],"iteration":314,"passed_time":0.5151139979,"remaining_time":1.120168535},
{"learn":[4.392838833],"iteration":315,"passed_time":0.5163294795,"remaining_time":1.11762457},
{"learn":[4.389213061],"iteration":316,"passed_time":0.5177440467,"remaining_time":1.11551793},
{"learn":[4.3861981],"iteration":317,"passed_time":0.5191808325,"remaining_time":1.113463295},
{"learn":[4.385054234],"iteration":318,"passed_time":0.5204210263,"remaining_time":1.110992849},
{"learn":[4.379364607],"iteration":319,"passed_time":0.5217540606,"remaining_time":1.108727379},
{"learn":[4.378387619],"iteration":320,"passed_time":0.5230933817,"remaining_time":1.106481016},
{"learn":[4.375816727],"iteration":321,"passed_time":0.5245102257,"remaining_time":1.104403519},
{"learn":[4.374600202],"iteration":322,"passed_time":0.5256806938,"remaining_time":1.101813714},
{"learn":[4.37098897],"iteration":323,"passed_time":0.526886873,"remaining_time":1.099307179},
{"learn":[4.367418484],"iteration":324,"passed_time":0.5282318599,"remaining_time":1.09709694},
{"learn":[4.363584638],"iteration":325,"passed_time":0.5294675742,"remaining_time":1.094666089},
{"learn":[4.360770706],"iteration":326,"passed_time":0.5307473928,"remaining_time":1.092333319},
{"learn":[4.358675808],"iteration":327,"passed_time":0.5319452957,"remaining_time":1.089839143},
{"learn":[4.354228195],"iteration":328,"passed_time":0.533173076,"remaining_time":1.087413781},
{"learn":[4.353773425],"iteration":329,"passed_time":0.5342639276,"remaining_time":1.084717671},
{"learn":[4.351648009],"iteration":330,"passed_time":0.5353595639,"remaining_time":1.082040931},
{"learn":[4.348209927],"iteration":331,"passed_time":0.5370059667,"remaining_time":1.080481885},
{"learn":[4.345852733],"iteration":332,"passed_time":0.5382522174,"remaining_time":1.078120808},
{"learn":[4.34237339],"iteration":333,"passed_time":0.5394501903,"remaining_time":1.07567014},
{"learn":[4.340814362],"iteration":334,"passed_time":0.5405698089,"remaining_time":1.073071412},
{"learn":[4.339707068],"iteration":335,"passed_time":0.54175871,"remaining_time":1.070618403},
{"learn":[4.335430786],"iteration":336,"passed_time":0.543030919,"remaining_time":1.068336793},
{"learn":[4.33521887],"iteration":337,"passed_time":0.5442354212,"remaining_time":1.065928547},
{"learn":[4.328507238],"iteration":338,"passed_time":0.5455985052,"remaining_time":1.063836613},
{"learn":[4.326140732],"iteration":339,"passed_time":0.5468268583,"remaining_time":1.061487431},
{"learn":[4.323785636],"iteration":340,"passed_time":0.5480869657,"remaining_time":1.059206189},
{"learn":[4.320632534],"iteration":341,"passed_time":0.5494250258,"remaining_time":1.057080898},
{"learn":[4.31973724],"iteration":342,"passed_time":0.5504953577,"remaining_time":1.054447376},
{"learn":[4.318000924],"iteration":343,"passed_time":0.5517948651,"remaining_time":1.052259975},
{"learn":[4.312713628],"iteration":344,"passed_time":0.5531612682,"remaining_time":1.050204727},
{"learn":[4.308220789],"iteration":345,"passed_time":0.554417707,"remaining_time":1.047945608},
{"learn":[4.305890947],"iteration":346,"passed_time":0.5556240671,"remaining_time":1.045598028},
{"learn":[4.305137856],"iteration":347,"passed_time":0.5568349809,"remaining_time":1.043265539},
{"learn":[4.304787172],"iteration":348,"passed_time":0.5579238323,"remaining_time":1.04071179},
{"learn":[4.30350134],"iteration":349,"passed_time":0.5591982343,"remaining_time":1.038511007},
{"learn":[4.30293809],"iteration":350,"passed_time":0.5603518266,"remaining_time":1.036092124},
{"learn":[4.299548459],"iteration":351,"passed_time":0.5615815164,"remaining_time":1.033820519},
{"learn":[4.294768408],"iteration":352,"passed_time":0.5631862611,"remaining_time":1.032242241},
{"learn":[4.294581479],"iteration":353,"passed_time":0.5645147206,"remaining_time":1.030159631},
{"learn":[4.292551604],"iteration":354,"passed_time":0.565903529,"remaining_time":1.028190919},
{"learn":[4.288628894],"iteration":355,"passed_time":0.5671022676,"remaining_time":1.02588163},
{"learn":[4.287802767],"iteration":356,"passed_time":0.5682382674,"remaining_time":1.023465563},
{"learn":[4.284566905],"iteration":357,"passed_time":0.5693817611,"remaining_time":1.021070085},
{"learn":[4.27890232],"iteration":358,"passed_time":0.5705344989,"remaining_time":1.018698089},
{"learn":[4.276938023],"iteration":359,"passed_time":0.5716953363,"remaining_time":1.016347265},
{"learn":[4.273425094],"iteration":360,"passed_time":0.5731797388,"remaining_time":1.01457577},
{"learn":[4.269726505],"iteration":361,"passed_time":0.5744705185,"remaining_time":1.012464616},
{"learn":[4.265565857],"iteration":362,"passed_time":0.5758483623,"remaining_time":1.010510763},
{"learn":[4.262117173],"iteration":363,"passed_time":0.5770378028,"remaining_time":1.008230886},
{"learn":[4.259185148],"iteration":364,"passed_time":0.5783095627,"remaining_time":1.006100198},
{"learn":[4.257668507],"iteration":365,"passed_time":0.5795436054,"remaining_time":1.003908868},
{"learn":[4.253432436],"iteration":366,"passed_time":0.5807462348,"remaining_time":1.001668574},
{"learn":[4.250216667],"iteration":367,"passed_time":0.582035924,"remaining_time":0.9995834347},
{"learn":[4.24514828],"iteration":368,"passed_time":0.583331878,"remaining_time":0.9975133199},
{"learn":[4.244015772],"iteration":369,"passed_time":0.5845877841,"remaining_time":0.9953792},
{"learn":[4.240329192],"iteration":370,"passed_time":0.5857486682,"remaining_time":0.9930887124},
{"learn":[4.236718014],"iteration":371,"passed_time":0.5870717339,"remaining_time":0.9910780884},
{"learn":[4.233495944],"iteration":372,"passed_time":0.5882342964,"remaining_time":0.9888013508},
{"learn":[4.230357491],"iteration":373,"passed_time":0.5894104171,"remaining_time":0.986553265},
{"learn":[4.227381215],"iteration":374,"passed_time":0.590504287,"remaining_time":0.9841738116},
{"learn":[4.226169067],"iteration":375,"passed_time":0.5916257384,"remaining_time":0.98184697},
{"learn":[4.225963861],"iteration":376,"passed_time":0.5927227248,"remaining_time":0.9794860943},
{"learn":[4.224346548],"iteration":377,"passed_time":0.5942416272,"remaining_time":0.9778261696},
{"learn":[4.222595381],"iteration":378,"passed_time":0.595775539,"remaining_time":0.9761915824},
{"learn":[4.219700938],"iteration":379,"passed_time":0.597216694,"remaining_time":0.974406185},
{"learn":[4.216356207],"iteration":380,"passed_time":0.5985525463,"remaining_time":0.9724515123},
{"learn":[4.214326494],"iteration":381,"passed_time":0.5998312913,"remaining_time":0.9704076912},
{"learn":[4.212901398],"iteration":382,"passed_time":0.6011696075,"remaining_time":0.9684638325},
{"learn":[4.211331091],"iteration":383,"passed_time":0.6023061513,"remaining_time":0.966199451},
{"learn":[4.208624791],"iteration":384,"passed_time":0.6035583879,"remaining_time":0.9641257366},
{"learn":[4.204659106],"iteration":385,"passed_time":0.604777098,"remaining_time":0.9620029486},
{"learn":[4.202968852],"iteration":386,"passed_time":0.6062887649,"remaining_time":0.9603488706},
{"learn":[4.197261935],"iteration":387,"passed_time":0.60738502,"remaining_time":0.9580402893},
{"learn":[4.196934403],"iteration":388,"passed_time":0.6085452336,"remaining_time":0.9558384003},
{"learn":[4.192479929],"iteration":389,"passed_time":0.6101701026,"remaining_time":0.954368622},
{"learn":[4.190243116],"iteration":390,"passed_time":0.6115155157,"remaining_time":0.9524627854},
{"learn":[4.185852431],"iteration":391,"passed_time":0.613030162,"remaining_time":0.950822292},
{"learn":[4.180967944],"iteration":392,"passed_time":0.6146249438,"remaining_time":0.949306211},
{"learn":[4.178283162],"iteration":393,"passed_time":0.6163113607,"remaining_time":0.9479306715},
{"learn":[4.176341157],"iteration":394,"passed_time":0.6174576609,"remaining_time":0.9457262907},
{"learn":[4.176041504],"iteration":395,"passed_time":0.618485231,"remaining_time":0.9433461604},
{"learn":[4.175564513],"iteration":396,"passed_time":0.6196603097,"remaining_time":0.9411968936},
{"learn":[4.170830274],"iteration":397,"passed_time":0.6209325449,"remaining_time":0.9391994774},
{"learn":[4.167804808],"iteration":398,"passed_time":0.6220280971,"remaining_time":0.9369395648},
{"learn":[4.165860548],"iteration":399,"passed_time":0.6230532442,"remaining_time":0.9345798663},
{"learn":[4.160950571],"iteration":400,"passed_time":0.6243758747,"remaining_time":0.9326711944},
{"learn":[4.158544115],"iteration":401,"passed_time":0.6262838751,"remaining_time":0.9316362122},
{"learn":[4.154448767],"iteration":402,"passed_time":0.6276437672,"remaining_time":0.9297849356},
{"learn":[4.15197457],"iteration":403,"passed_time":0.628882823,"remaining_time":0.927757828},
{"learn":[4.149562679],"iteration":404,"passed_time":0.6304542059,"remaining_time":0.9262228456},
{"learn":[4.149327961],"iteration":405,"passed_time":0.6316024383,"remaining_time":0.924068592},
{"learn":[4.147444889],"iteration":406,"passed_time":0.6326630771,"remaining_time":0.9217916578},
{"learn":[4.147254809],"iteration":407,"passed_time":0.6337517623,"remaining_time":0.9195613805},
{"learn":[4.144589165],"iteration":408,"passed_time":0.6348994682,"remaining_time":0.9174219699},
{"learn":[4.141691034],"iteration":409,"passed_time":0.6360454875,"remaining_time":0.9152849698},
{"learn":[4.138893468],"iteration":410,"passed_time":0.6370734241,"remaining_time":0.9129835688},
{"learn":[4.136964597],"iteration":411,"passed_time":0.6381158817,"remaining_time":0.9107090738},
{"learn":[4.133773523],"iteration":412,"passed_time":0.6391921235,"remaining_time":0.908488563},
{"learn":[4.131363444],"iteration":413,"passed_time":0.6407674609,"remaining_time":0.9069800291},
{"learn":[4.130228592],"iteration":414,"passed_time":0.6418372693,"remaining_time":0.9047585604},
{"learn":[4.12884186],"iteration":415,"passed_time":0.6431213506,"remaining_time":0.9028434345},
{"learn":[4.12413494],"iteration":416,"passed_time":0.644361419,"remaining_time":0.9008698017},
{"learn":[4.119422508],"iteration":417,"passed_time":0.6459609123,"remaining_time":0.8994001219},
{"learn":[4.117038244],"iteration":418,"passed_time":0.6472423333,"remaining_time":0.8974887725},
{"learn":[4.116067631],"iteration":419,"passed_time":0.6485548175,"remaining_time":0.8956233194},
{"learn":[4.110343455],"iteration":420,"passed_time":0.6499130122,"remaining_time":0.8938233589},
{"learn":[4.105604544],"iteration":421,"passed_time":0.6510569473,"remaining_time":0.8917320273},
{"learn":[4.103390131],"iteration":422,"passed_time":0.6521691113,"remaining_time":0.8896018374},
{"learn":[4.096724402],"iteration":423,"passed_time":0.6532938618,"remaining_time":0.8874935481},
{"learn":[4.093431279],"iteration":424,"passed_time":0.6547531459,"remaining_time":0.8858424915},
{"learn":[4.091412744],"iteration":425,"passed_time":0.6559525889,"remaining_time":0.8838422207},
{"learn":[4.091192901],"iteration":426,"passed_time":0.6572411443,"remaining_time":0.8819652826},
{"learn":[4.088994581],"iteration":427,"passed_time":0.6583956076,"remaining_time":0.8799118869},
{"learn":[4.087845355],"iteration":428,"passed_time":0.6598514735,"remaining_time":0.8782638493},
{"learn":[4.083650279],"iteration":429,"passed_time":0.6611953872,"remaining_time":0.8764683039},
{"learn":[4.079840652],"iteration":430,"passed_time":0.6624962049,"remaining_time":0.8746179596},
{"learn":[4.075707828],"iteration":431,"passed_time":0.6638834876,"remaining_time":0.8728838449},
{"learn":[4.071345409],"iteration":432,"passed_time":0.6651186198,"remaining_time":0.8709520957},
{"learn":[4.067460475],"iteration":433,"passed_time":0.6663075464,"remaining_time":0.8689632978},
{"learn":[4.064914749],"iteration":434,"passed_time":0.6676259293,"remaining_time":0.8671463219},
{"learn":[4.063823175],"iteration":435,"passed_time":0.6686899597,"remaining_time":0.8650026084},
{"learn":[4.058898471],"iteration":436,"passed_time":0.6698606303,"remaining_time":0.8630012239},
{"learn":[4.054120355],"iteration":437,"passed_time":0.671171905,"remaining_time":0.8611840425},
{"learn":[4.052715901],"iteration":438,"passed_time":0.6723981561,"remaining_time":0.8592605138},
{"learn":[4.052114167],"iteration":439,"passed_time":0.6736366845,"remaining_time":0.8573557803},
{"learn":[4.051377267],"iteration":440,"passed_time":0.6748306342,"remaining_time":0.8553975612},
{"learn":[4.049275336],"iteration":441,"passed_time":0.6764172845,"remaining_time":0.8539385628},
{"learn":[4.047099198],"iteration":442,"passed_time":0.6776248278,"remaining_time":0.852002323},
{"learn":[4.044348685],"iteration":443,"passed_time":0.6790120557,"remaining_time":0.8502943761},
{"learn":[4.042822379],"iteration":444,"passed_time":0.6800978091,"remaining_time":0.8482118742},
{"learn":[4.041258611],"iteration":445,"passed_time":0.6812604715,"remaining_time":0.8462293749},
{"learn":[4.040044254],"iteration":446,"passed_time":0.6824845977,"remaining_time":0.8443265829},
{"learn":[4.036860137],"iteration":447,"passed_time":0.6836772578,"remaining_time":0.8423880498},
{"learn":[4.036372284],"iteration":448,"passed_time":0.6852740622,"remaining_time":0.8409487935},
{"learn":[4.03368231],"iteration":449,"passed_time":0.6866311171,"remaining_time":0.8392158097},
{"learn":[4.032439519],"iteration":450,"passed_time":0.687802104,"remaining_time":0.8372579935},
{"learn":[4.032008634],"iteration":451,"passed_time":0.6888782208,"remaining_time":0.8351886394},
{"learn":[4.030034932],"iteration":452,"passed_time":0.6900364987,"remaining_time":0.8332228803},
{"learn":[4.028173412],"iteration":453,"passed_time":0.6912070045,"remaining_time":0.8312753843},
{"learn":[4.023806097],"iteration":454,"passed_time":0.6924570134,"remaining_time":0.8294265325},
{"learn":[4.020239186],"iteration":455,"passed_time":0.6936376471,"remaining_time":0.827497544},
{"learn":[4.017384838],"iteration":456,"passed_time":0.6947918115,"remaining_time":0.82554038},
{"learn":[4.016468229],"iteration":457,"passed_time":0.6960317476,"remaining_time":0.8236882254},
{"learn":[4.014530169],"iteration":458,"passed_time":0.6972302166,"remaining_time":0.8217898631},
{"learn":[4.012884822],"iteration":459,"passed_time":0.6983560402,"remaining_time":0.8198092646},
{"learn":[4.008924707],"iteration":460,"passed_time":0.6996323904,"remaining_time":0.8180083697},
{"learn":[4.008286778],"iteration":461,"passed_time":0.7008579119,"remaining_time":0.8161505555},
{"learn":[4.006444202],"iteration":462,"passed_time":0.7020416712,"remaining_time":0.8142470355},
{"learn":[4.003284363],"iteration":463,"passed_time":0.7032026239,"remaining_time":0.8123202725},
{"learn":[3.999811484],"iteration":464,"passed_time":0.7043116077,"remaining_time":0.810337011},
{"learn":[3.997483319],"iteration":465,"passed_time":0.7054364705,"remaining_time":0.8083756979},
{"learn":[3.99708333],"iteration":466,"passed_time":0.7065920279,"remaining_time":0.8064529997},
{"learn":[3.995860263],"iteration":467,"passed_time":0.7077413898,"remaining_time":0.8045265372},
{"learn":[3.994131111],"iteration":468,"passed_time":0.7089407009,"remaining_time":0.8026599407},
{"learn":[3.993125499],"iteration":469,"passed_time":0.7100865007,"remaining_time":0.8007358412},
{"learn":[3.992954084],"iteration":470,"passed_time":0.7110629629,"remaining_time":0.7986248564},
{"learn":[3.990635743],"iteration":471,"passed_time":0.7122066719,"remaining_time":0.7967057685},
{"learn":[3.986678254],"iteration":472,"passed_time":0.7132994952,"remaining_time":0.7947332642},
{"learn":[3.986393291],"iteration":473,"passed_time":0.7144380541,"remaining_time":0.7928152246},
{"learn":[3.986152671],"iteration":474,"passed_time":0.7155296499,"remaining_time":0.7908485604},
{"learn":[3.985596662],"iteration":475,"passed_time":0.71662423,"remaining_time":0.7888888582},
{"learn":[3.983853457],"iteration":476,"passed_time":0.7177466986,"remaining_time":0.7869633614},
{"learn":[3.983263928],"iteration":477,"passed_time":0.7188990457,"remaining_time":0.7850738532},
{"learn":[3.980067202],"iteration":478,"passed_time":0.7201023671,"remaining_time":0.783242867},
{"learn":[3.978115407],"iteration":479,"passed_time":0.7212721782,"remaining_time":0.7813781931},
{"learn":[3.972661644],"iteration":480,"passed_time":0.7223334146,"remaining_time":0.779399256},
{"learn":[3.969938254],"iteration":481,"passed_time":0.723454133,"remaining_time":0.7774880517},
{"learn":[3.968211434],"iteration":482,"passed_time":0.7245420922,"remaining_time":0.7755450552},
{"learn":[3.966113368],"iteration":483,"passed_time":0.7255697903,"remaining_time":0.7735413467},
{"learn":[3.962246044],"iteration":484,"passed_time":0.726725504,"remaining_time":0.771677597},
{"learn":[3.961319703],"iteration":485,"passed_time":0.7277749073,"remaining_time":0.7697043258},
{"learn":[3.96078191],"iteration":486,"passed_time":0.7287973729,"remaining_time":0.7677064729},
{"learn":[3.958913633],"iteration":487,"passed_time":0.7300017367,"remaining_time":0.7659034615},
{"learn":[3.957428286],"iteration":488,"passed_time":0.7311967897,"remaining_time":0.7640931688},
{"learn":[3.952641965],"iteration":489,"passed_time":0.7323893537,"remaining_time":0.7622827967},
{"learn":[3.951486786],"iteration":490,"passed_time":0.7335318093,"remaining_time":0.7604229958},
{"learn":[3.94938344],"iteration":491,"passed_time":0.7346542914,"remaining_time":0.7585454879},
{"learn":[3.947297924],"iteration":492,"passed_time":0.7355983493,"remaining_time":0.7564875519},
{"learn":[3.946284886],"iteration":493,"passed_time":0.7367198929,"remaining_time":0.7546159227},
{"learn":[3.943288204],"iteration":494,"passed_time":0.7378450133,"remaining_time":0.7527509732},
{"learn":[3.943076488],"iteration":495,"passed_time":0.7389291946,"remaining_time":0.7508474074},
{"learn":[3.942347078],"iteration":496,"passed_time":0.7400945304,"remaining_time":0.7490292733},
{"learn":[3.940251541],"iteration":497,"passed_time":0.7412343389,"remaining_time":0.7471880284},
{"learn":[3.939011019],"iteration":498,"passed_time":0.7424584721,"remaining_time":0.7454342576},
{"learn":[3.938760512],"iteration":499,"passed_time":0.7438045125,"remaining_time":0.7438045125},
{"learn":[3.934522727],"iteration":500,"passed_time":0.7450326164,"remaining_time":0.7420584343},
{"learn":[3.930091193],"iteration":501,"passed_time":0.7463136065,"remaining_time":0.7403668846},
{"learn":[3.927671752],"iteration":502,"passed_time":0.7474576407,"remaining_time":0.738541645},
{"learn":[3.927280041],"iteration":503,"passed_time":0.7485508008,"remaining_time":0.736669042},
{"learn":[3.925987561],"iteration":504,"passed_time":0.7496776186,"remaining_time":0.7348325172},
{"learn":[3.921645957],"iteration":505,"passed_time":0.7508820429,"remaining_time":0.7330745636},
{"learn":[3.920333743],"iteration":506,"passed_time":0.7520361151,"remaining_time":0.7312698319},
{"learn":[3.918659461],"iteration":507,"passed_time":0.7532298314,"remaining_time":0.7295060572},
{"learn":[3.916124385],"iteration":508,"passed_time":0.7543633638,"remaining_time":0.7276864669},
{"learn":[3.913849268],"iteration":509,"passed_time":0.755464924,"remaining_time":0.7258388485},
{"learn":[3.912826119],"iteration":510,"passed_time":0.7565834485,"remaining_time":0.7240103842},
{"learn":[3.910034145],"iteration":511,"passed_time":0.7576292307,"remaining_time":0.7221153605},
{"learn":[3.90792379],"iteration":512,"passed_time":0.7588645835,"remaining_time":0.7204036105},
{"learn":[3.907823851],"iteration":513,"passed_time":0.7601287419,"remaining_time":0.7187209505},
{"learn":[3.904527401],"iteration":514,"passed_time":0.7614220831,"remaining_time":0.7170673987},
{"learn":[3.903378283],"iteration":515,"passed_time":0.7625543121,"remaining_time":0.7152641222},
{"learn":[3.902170135],"iteration":516,"passed_time":0.7637421751,"remaining_time":0.713515417},
{"learn":[3.899435429],"iteration":517,"passed_time":0.7649687444,"remaining_time":0.7118048934},
{"learn":[3.897497505],"iteration":518,"passed_time":0.7660359736,"remaining_time":0.7099485613},
{"learn":[3.896426119],"iteration":519,"passed_time":0.7671344237,"remaining_time":0.7081240834},
{"learn":[3.896044669],"iteration":520,"passed_time":0.7681691131,"remaining_time":0.7062437719},
{"learn":[3.892795942],"iteration":521,"passed_time":0.7693761437,"remaining_time":0.7045245147},
{"learn":[3.892413888],"iteration":522,"passed_time":0.7705789351,"remaining_time":0.70280335},
{"learn":[3.891738985],"iteration":523,"passed_time":0.7718266228,"remaining_time":0.7011249475},
{"learn":[3.88822057],"iteration":524,"passed_time":0.7730071578,"remaining_time":0.6993874285},
{"learn":[3.883837053],"iteration":525,"passed_time":0.7741668213,"remaining_time":0.6976332192},
{"learn":[3.881769742],"iteration":526,"passed_time":0.7754073855,"remaining_time":0.6959538773},
{"learn":[3.880356898],"iteration":527,"passed_time":0.7765182078,"remaining_time":0.6941602161},
{"learn":[3.879250273],"iteration":528,"passed_time":0.7776309521,"remaining_time":0.6923708477},
{"learn":[3.877174493],"iteration":529,"passed_time":0.7787600405,"remaining_time":0.6905985265},
{"learn":[3.875854201],"iteration":530,"passed_time":0.7798085709,"remaining_time":0.688757476},
{"learn":[3.873189396],"iteration":531,"passed_time":0.7809325679,"remaining_time":0.6869857928},
{"learn":[3.871583368],"iteration":532,"passed_time":0.7821597444,"remaining_time":0.6853069431},
{"learn":[3.869622679],"iteration":533,"passed_time":0.7832006559,"remaining_time":0.683467239},
{"learn":[3.866860164],"iteration":534,"passed_time":0.7842789805,"remaining_time":0.6816630391},
{"learn":[3.864498444],"iteration":535,"passed_time":0.785258488,"remaining_time":0.6797760045},
{"learn":[3.861416322],"iteration":536,"passed_time":0.7863280171,"remaining_time":0.6779699663},
{"learn":[3.860265769],"iteration":537,"passed_time":0.787406618,"remaining_time":0.6761744563},
{"learn":[3.859328725],"iteration":538,"passed_time":0.7885715776,"remaining_time":0.6744554681},
{"learn":[3.858521278],"iteration":539,"passed_time":0.7897426915,"remaining_time":0.6727437742},
{"learn":[3.85599111],"iteration":540,"passed_time":0.7908455223,"remaining_time":0.6709761455},
{"learn":[3.852379816],"iteration":541,"passed_time":0.7920242943,"remaining_time":0.6692751417},
{"learn":[3.851327537],"iteration":542,"passed_time":0.7932502017,"remaining_time":0.6676157314},
{"learn":[3.847854898],"iteration":543,"passed_time":0.7943076872,"remaining_time":0.6658167378},
{"learn":[3.847083414],"iteration":544,"passed_time":0.7954572097,"remaining_time":0.6640973035},
{"learn":[3.845397429],"iteration":545,"passed_time":0.7964935073,"remaining_time":0.6622858101},
{"learn":[3.841933528],"iteration":546,"passed_time":0.7976385742,"remaining_time":0.6605672287},
{"learn":[3.840996474],"iteration":547,"passed_time":0.7987875882,"remaining_time":0.6588539961},
{"learn":[3.838355966],"iteration":548,"passed_time":0.7998231182,"remaining_time":0.6570495926},
{"learn":[3.83342799],"iteration":549,"passed_time":0.8008622073,"remaining_time":0.6552508969},
{"learn":[3.828161535],"iteration":550,"passed_time":0.8019243012,"remaining_time":0.6534737046},
{"learn":[3.823502399],"iteration":551,"passed_time":0.8030689854,"remaining_time":0.6517661331},
{"learn":[3.820068862],"iteration":552,"passed_time":0.8043179014,"remaining_time":0.6501448498},
{"learn":[3.817951642],"iteration":553,"passed_time":0.8054748958,"remaining_time":0.6484509089},
{"learn":[3.815785958],"iteration":554,"passed_time":0.8065819172,"remaining_time":0.6467188345},
{"learn":[3.81503012],"iteration":555,"passed_time":0.807570538,"remaining_time":0.6448944584},
{"learn":[3.813529315],"iteration":556,"passed_time":0.8086308319,"remaining_time":0.6431300871},
{"learn":[3.808881326],"iteration":557,"passed_time":0.8097597444,"remaining_time":0.6414225932},
{"learn":[3.808740434],"iteration":558,"passed_time":0.810784081,"remaining_time":0.6396346686},
{"learn":[3.80714352],"iteration":559,"passed_time":0.8118627227,"remaining_time":0.6378921393},
{"learn":[3.80573346],"iteration":560,"passed_time":0.8129070521,"remaining_time":0.6361251263},
{"learn":[3.803370052],"iteration":561,"passed_time":0.8140023528,"remaining_time":0.6344004102},
{"learn":[3.803215211],"iteration":562,"passed_time":0.8150868628,"remaining_time":0.6326695542},
{"learn":[3.801309667],"iteration":563,"passed_time":0.8161583987,"remaining_time":0.6309309607},
{"learn":[3.800003847],"iteration":564,"passed_time":0.8173289485,"remaining_time":0.6292709604},
{"learn":[3.798026138],"iteration":565,"passed_time":0.8184995045,"remaining_time":0.6276126943},
{"learn":[3.794745847],"iteration":566,"passed_time":0.8200878476,"remaining_time":0.6262751993},
{"learn":[3.794312041],"iteration":567,"passed_time":0.8211410503,"remaining_time":0.6245298129},
{"learn":[3.792205926],"iteration":568,"passed_time":0.8224441734,"remaining_time":0.6229761665},
{"learn":[3.788991061],"iteration":569,"passed_time":0.8234363711,"remaining_time":0.6211888413},
{"learn":[3.787391572],"iteration":570,"passed_time":0.8245188488,"remaining_time":0.6194721299},
{"learn":[3.7826445],"iteration":571,"passed_time":0.8255335035,"remaining_time":0.6177068872},
{"learn":[3.781700331],"iteration":572,"passed_time":0.8265767743,"remaining_time":0.6159655892},
{"learn":[3.780045374],"iteration":573,"passed_time":0.82758535,"remaining_time":0.6142009741},
{"learn":[3.775462644],"iteration":574,"passed_time":0.8286086775,"remaining_time":0.612449892},
{"learn":[3.773711943],"iteration":575,"passed_time":0.8296957513,"remaining_time":0.6107482614},
{"learn":[3.772415806],"iteration":576,"passed_time":0.8306990381,"remaining_time":0.6089873365},
{"learn":[3.770170875],"iteration":577,"passed_time":0.8317189492,"remaining_time":0.6072411706},
{"learn":[3.765166479],"iteration":578,"passed_time":0.8328416594,"remaining_time":0.6055722601},
{"learn":[3.763976102],"iteration":579,"passed_time":0.8341054791,"remaining_time":0.6040074159},
{"learn":[3.760761708],"iteration":580,"passed_time":0.8356657102,"remaining_time":0.602657371},
{"learn":[3.758155662],"iteration":581,"passed_time":0.8370055424,"remaining_time":0.6011483106},
{"learn":[3.756844548],"iteration":582,"passed_time":0.8380315479,"remaining_time":0.599415361},
{"learn":[3.753098923],"iteration":583,"passed_time":0.8393705793,"remaining_time":0.5979078099},
{"learn":[3.751618946],"iteration":584,"passed_time":0.840588247,"remaining_time":0.5963147393},
{"learn":[3.751398464],"iteration":585,"passed_time":0.8416667919,"remaining_time":0.5946246619},
{"learn":[3.749920103],"iteration":586,"passed_time":0.8429087356,"remaining_time":0.5930516317},
{"learn":[3.748237465],"iteration":587,"passed_time":0.844023973,"remaining_time":0.5913909471},
{"learn":[3.746021536],"iteration":588,"passed_time":0.8452018277,"remaining_time":0.5897758085},
{"learn":[3.74417648],"iteration":589,"passed_time":0.8463023455,"remaining_time":0.5881084096},
{"learn":[3.738788389],"iteration":590,"passed_time":0.8473272041,"remaining_time":0.5863905693},
{"learn":[3.736021611],"iteration":591,"passed_time":0.8483705601,"remaining_time":0.5846878185},
{"learn":[3.734546151],"iteration":592,"passed_time":0.8495512101,"remaining_time":0.5830815219},
{"learn":[3.733527479],"iteration":593,"passed_time":0.8507646413,"remaining_time":0.5814990646},
{"learn":[3.733026392],"iteration":594,"passed_time":0.8519279642,"remaining_time":0.5798837404},
{"learn":[3.730314752],"iteration":595,"passed_time":0.8531385678,"remaining_time":0.5783019822},
{"learn":[3.727342596],"iteration":596,"passed_time":0.8542109763,"remaining_time":0.57662818},
{"learn":[3.725459604],"iteration":597,"passed_time":0.8553900404,"remaining_time":0.5750280874},
{"learn":[3.723158842],"iteration":598,"passed_time":0.8565536449,"remaining_time":0.5734190511},
{"learn":[3.722362756],"iteration":599,"passed_time":0.8576129582,"remaining_time":0.5717419721},
{"learn":[3.721443615],"iteration":600,"passed_time":0.858682183,"remaining_time":0.5700735291},
{"learn":[3.720743486],"iteration":601,"passed_time":0.8597935118,"remaining_time":0.5684349131},
{"learn":[3.720215334],"iteration":602,"passed_time":0.8607066748,"remaining_time":0.5666675786},
{"learn":[3.719436563],"iteration":603,"passed_time":0.8617835123,"remaining_time":0.5650103822},
{"learn":[3.715046574],"iteration":604,"passed_time":0.8628722167,"remaining_time":0.5633628522},
{"learn":[3.71443396],"iteration":605,"passed_time":0.8640465941,"remaining_time":0.5617728681},
{"learn":[3.712938941],"iteration":606,"passed_time":0.8653801955,"remaining_time":0.5602873424},
{"learn":[3.712814764],"iteration":607,"passed_time":0.8665205688,"remaining_time":0.5586777351},
{"learn":[3.71235348],"iteration":608,"passed_time":0.867538818,"remaining_time":0.5569912608},
{"learn":[3.711223749],"iteration":609,"passed_time":0.8685893103,"remaining_time":0.5553275918},
{"learn":[3.710755648],"iteration":610,"passed_time":0.8697436039,"remaining_time":0.5537320163},
{"learn":[3.708668039],"iteration":611,"passed_time":0.8708002466,"remaining_time":0.5520759733},
{"learn":[3.705623591],"iteration":612,"passed_time":0.8718410056,"remaining_time":0.5504118584},
{"learn":[3.704045802],"iteration":613,"passed_time":0.8728523755,"remaining_time":0.5487312979},
{"learn":[3.699915209],"iteration":614,"passed_time":0.8738751864,"remaining_time":0.547060076},
{"learn":[3.696182221],"iteration":615,"passed_time":0.8749773753,"remaining_time":0.5454404417},
{"learn":[3.694263278],"iteration":616,"passed_time":0.8760169119,"remaining_time":0.5437835936},
{"learn":[3.693810229],"iteration":617,"passed_time":0.877076523,"remaining_time":0.5421411517},
{"learn":[3.690900932],"iteration":618,"passed_time":0.8781321788,"remaining_time":0.5404981585},
{"learn":[3.688020895],"iteration":619,"passed_time":0.879169633,"remaining_time":0.5388459041},
{"learn":[3.685491894],"iteration":620,"passed_time":0.8802080451,"remaining_time":0.5371962143},
{"learn":[3.684328128],"iteration":621,"passed_time":0.8813247006,"remaining_time":0.5355960399},
{"learn":[3.680640153],"iteration":622,"passed_time":0.8823404582,"remaining_time":0.5339363607},
{"learn":[3.678932783],"iteration":623,"passed_time":0.8834386945,"remaining_time":0.5323284441},
{"learn":[3.674167041],"iteration":624,"passed_time":0.8843824765,"remaining_time":0.5306294859},
{"learn":[3.672200976],"iteration":625,"passed_time":0.8854405936,"remaining_time":0.5290012492},
{"learn":[3.670606604],"iteration":626,"passed_time":0.8864970499,"remaining_time":0.5273738431},
{"learn":[3.665506042],"iteration":627,"passed_time":0.8875544872,"remaining_time":0.5257488363},
{"learn":[3.664214007],"iteration":628,"passed_time":0.8886832099,"remaining_time":0.5241676802},
{"learn":[3.66261643],"iteration":629,"passed_time":0.8897246209,"remaining_time":0.5225366821},
{"learn":[3.662118449],"iteration":630,"passed_time":0.8908801528,"remaining_time":0.5209742891},
{"learn":[3.660871366],"iteration":631,"passed_time":0.8920030659,"remaining_time":0.5193941903},
{"learn":[3.656695243],"iteration":632,"passed_time":0.8932244378,"remaining_time":0.5178726203},
{"learn":[3.654497801],"iteration":633,"passed_time":0.8945971547,"remaining_time":0.5164393669},
{"learn":[3.654189134],"iteration":634,"passed_time":0.8957997548,"remaining_time":0.5149085205},
{"learn":[3.653957699],"iteration":635,"passed_time":0.8968918686,"remaining_time":0.513315472},
{"learn":[3.651920725],"iteration":636,"passed_time":0.8979677282,"remaining_time":0.5117147337},
{"learn":[3.65106705],"iteration":637,"passed_time":0.899069889,"remaining_time":0.510130564},
{"learn":[3.650612844],"iteration":638,"passed_time":0.9002456956,"remaining_time":0.5085895088},
{"learn":[3.649884732],"iteration":639,"passed_time":0.9014058896,"remaining_time":0.5070408129},
{"learn":[3.646276182],"iteration":640,"passed_time":0.9025873404,"remaining_time":0.5055052343},
{"learn":[3.645808194],"iteration":641,"passed_time":0.9037064402,"remaining_time":0.50393599},
{"learn":[3.645042989],"iteration":642,"passed_time":0.9048405381,"remaining_time":0.502376473},
{"learn":[3.639864499],"iteration":643,"passed_time":0.9059977744,"remaining_time":0.5008310678},
{"learn":[3.637318478],"iteration":644,"passed_time":0.9072375161,"remaining_time":0.4993322763},
{"learn":[3.636344905],"iteration":645,"passed_time":0.9086878087,"remaining_time":0.4979496661},
{"learn":[3.634754643],"iteration":646,"passed_time":0.9100052912,"remaining_time":0.4964943861},
{"learn":[3.630724975],"iteration":647,"passed_time":0.9112026974,"remaining_time":0.4949743047},
{"learn":[3.629408252],"iteration":648,"passed_time":0.9124466817,"remaining_time":0.4934804087},
{"learn":[3.62790646],"iteration":649,"passed_time":0.9138626982,"remaining_time":0.4920799144},
{"learn":[3.627388973],"iteration":650,"passed_time":0.915072558,"remaining_time":0.4905688522},
{"learn":[3.625163557],"iteration":651,"passed_time":0.9163784047,"remaining_time":0.4891099461},
{"learn":[3.623701985],"iteration":652,"passed_time":0.9175380689,"remaining_time":0.4875738284},
{"learn":[3.622342639],"iteration":653,"passed_time":0.9187771637,"remaining_time":0.4860808848},
{"learn":[3.621130639],"iteration":654,"passed_time":0.9199888571,"remaining_time":0.4845742835},
{"learn":[3.619125665],"iteration":655,"passed_time":0.921420945,"remaining_time":0.4831841541},
{"learn":[3.618878783],"iteration":656,"passed_time":0.9226026747,"remaining_time":0.4816631924},
{"learn":[3.616207429],"iteration":657,"passed_time":0.924038461,"remaining_time":0.4802753095},
{"learn":[3.61206486],"iteration":658,"passed_time":0.9253690685,"remaining_time":0.4788328564},
{"learn":[3.611955873],"iteration":659,"passed_time":0.926460822,"remaining_time":0.4772676962},
{"learn":[3.610713743],"iteration":660,"passed_time":0.9276746572,"remaining_time":0.4757665791},
{"learn":[3.610044025],"iteration":661,"passed_time":0.9289577501,"remaining_time":0.4743016912},
{"learn":[3.607342669],"iteration":662,"passed_time":0.93014186,"remaining_time":0.472787039},
{"learn":[3.602510618],"iteration":663,"passed_time":0.9313045885,"remaining_time":0.4712625628},
{"learn":[3.600492392],"iteration":664,"passed_time":0.9324898707,"remaining_time":0.4697505364},
{"learn":[3.597171065],"iteration":665,"passed_time":0.9337936631,"remaining_time":0.4682989242},
{"learn":[3.594358798],"iteration":666,"passed_time":0.9350715166,"remaining_time":0.4668348051},
{"learn":[3.593945251],"iteration":667,"passed_time":0.93648261,"remaining_time":0.4654374648},
{"learn":[3.593607748],"iteration":668,"passed_time":0.93772374,"remaining_time":0.463955991},
{"learn":[3.592238714],"iteration":669,"passed_time":0.9390425554,"remaining_time":0.4625134974},
{"learn":[3.590144654],"iteration":670,"passed_time":0.9403662479,"remaining_time":0.4610737639},
{"learn":[3.587151536],"iteration":671,"passed_time":0.9415459242,"remaining_time":0.4595640821},
{"learn":[3.586070865],"iteration":672,"passed_time":0.9428011988,"remaining_time":0.4580921129},
{"learn":[3.585102746],"iteration":673,"passed_time":0.944046732,"remaining_time":0.4566160751},
{"learn":[3.584362847],"iteration":674,"passed_time":0.9452432794,"remaining_time":0.4551171345},
{"learn":[3.581407561],"iteration":675,"passed_time":0.9464523854,"remaining_time":0.4536251078},
{"learn":[3.57919422],"iteration":676,"passed_time":0.9477043995,"remaining_time":0.4521543885},
{"learn":[3.577632204],"iteration":677,"passed_time":0.9490851477,"remaining_time":0.4507454536},
{"learn":[3.573911195],"iteration":678,"passed_time":0.9504936244,"remaining_time":0.4493497105},
{"learn":[3.573408216],"iteration":679,"passed_time":0.9519030721,"remaining_time":0.4479543869},
{"learn":[3.571076482],"iteration":680,"passed_time":0.9533011798,"remaining_time":0.4465537098},
{"learn":[3.568177107],"iteration":681,"passed_time":0.9545838685,"remaining_time":0.4450992232},
{"learn":[3.564824621],"iteration":682,"passed_time":0.9558544569,"remaining_time":0.4436396235},
{"learn":[3.562475026],"iteration":683,"passed_time":0.9571424838,"remaining_time":0.4421886329},
{"learn":[3.561226889],"iteration":684,"passed_time":0.9585853477,"remaining_time":0.4408093205},
{"learn":[3.559383467],"iteration":685,"passed_time":0.9599175152,"remaining_time":0.4393791542},
{"learn":[3.555209766],"iteration":686,"passed_time":0.9610848921,"remaining_time":0.4378741939},
{"learn":[3.55345383],"iteration":687,"passed_time":0.9622859198,"remaining_time":0.4363854753},
{"learn":[3.552300968],"iteration":688,"passed_time":0.9635013154,"remaining_time":0.434904077},
{"learn":[3.551253986],"iteration":689,"passed_time":0.9647965531,"remaining_time":0.4334593209},
{"learn":[3.549807725],"iteration":690,"passed_time":0.9661969885,"remaining_time":0.4320620397},
{"learn":[3.547992926],"iteration":691,"passed_time":0.9673514275,"remaining_time":0.4305552597},
{"learn":[3.545438607],"iteration":692,"passed_time":0.9685945188,"remaining_time":0.4290887695},
{"learn":[3.543313763],"iteration":693,"passed_time":0.9697558542,"remaining_time":0.4275868752},
{"learn":[3.542962896],"iteration":694,"passed_time":0.970953873,"remaining_time":0.4261020594},
{"learn":[3.539800465],"iteration":695,"passed_time":0.9722536098,"remaining_time":0.4246624962},
{"learn":[3.53953187],"iteration":696,"passed_time":0.9734523557,"remaining_time":0.4231794315},
{"learn":[3.536332425],"iteration":697,"passed_time":0.9747135923,"remaining_time":0.421724219},
{"learn":[3.534993327],"iteration":698,"passed_time":0.9759338173,"remaining_time":0.4202519013},
{"learn":[3.531637011],"iteration":699,"passed_time":0.9774453558,"remaining_time":0.4189051525},
{"learn":[3.531040284],"iteration":700,"passed_time":0.9788020549,"remaining_time":0.4174918893},
{"learn":[3.529973872],"iteration":701,"passed_time":0.9800591939,"remaining_time":0.4160365239},
{"learn":[3.527325183],"iteration":702,"passed_time":0.9814067326,"remaining_time":0.4146199141},
{"learn":[3.527200815],"iteration":703,"passed_time":0.9826446658,"remaining_time":0.4131574163},
{"learn":[3.523459911],"iteration":704,"passed_time":0.9840047975,"remaining_time":0.4117466883},
{"learn":[3.522729934],"iteration":705,"passed_time":0.985521248,"remaining_time":0.4104011996},
{"learn":[3.522260582],"iteration":706,"passed_time":0.986942752,"remaining_time":0.4090158788},
{"learn":[3.518641591],"iteration":707,"passed_time":0.9882193506,"remaining_time":0.4075706926},
{"learn":[3.516856405],"iteration":708,"passed_time":0.9894199088,"remaining_time":0.4060947722},
{"learn":[3.515083413],"iteration":709,"passed_time":0.9906517427,"remaining_time":0.4046324019},
{"learn":[3.514671214],"iteration":710,"passed_time":0.9917773966,"remaining_time":0.4031275213},
{"learn":[3.512617621],"iteration":711,"passed_time":0.9929511718,"remaining_time":0.4016431706},
{"learn":[3.510747971],"iteration":712,"passed_time":0.994139259,"remaining_time":0.4001654521},
{"learn":[3.508149266],"iteration":713,"passed_time":0.995358628,"remaining_time":0.3987010751},
{"learn":[3.504557165],"iteration":714,"passed_time":0.9966306656,"remaining_time":0.3972583772},
{"learn":[3.501367208],"iteration":715,"passed_time":0.9979027083,"remaining_time":0.3958161581},
{"learn":[3.497593362],"iteration":716,"passed_time":0.9991259191,"remaining_time":0.3943551396},
{"learn":[3.496291169],"iteration":717,"passed_time":1.00047915,"remaining_time":0.3929458501},
{"learn":[3.49330374],"iteration":718,"passed_time":1.001950319,"remaining_time":0.391582809},
{"learn":[3.490044385],"iteration":719,"passed_time":1.003219719,"remaining_time":0.3901410018},
{"learn":[3.488891789],"iteration":720,"passed_time":1.004567824,"remaining_time":0.3887301288},
{"learn":[3.486869081],"iteration":721,"passed_time":1.005677827,"remaining_time":0.3872277505},
{"learn":[3.486303638],"iteration":722,"passed_time":1.006830225,"remaining_time":0.3857427003},
{"learn":[3.486035862],"iteration":723,"passed_time":1.007961086,"remaining_time":0.3842503588},
{"learn":[3.482668951],"iteration":724,"passed_time":1.009361636,"remaining_time":0.3828613103},
{"learn":[3.47820549],"iteration":725,"passed_time":1.010540675,"remaining_time":0.3813886295},
{"learn":[3.474392283],"iteration":726,"passed_time":1.011773914,"remaining_time":0.3799371093},
{"learn":[3.472268163],"iteration":727,"passed_time":1.01317468,"remaining_time":0.3785487817},
{"learn":[3.471209164],"iteration":728,"passed_time":1.014405337,"remaining_time":0.3770971829},
{"learn":[3.470049971],"iteration":729,"passed_time":1.015776002,"remaining_time":0.3756979732},
{"learn":[3.469078654],"iteration":730,"passed_time":1.017085633,"remaining_time":0.3742763821},
{"learn":[3.468643292],"iteration":731,"passed_time":1.018376433,"remaining_time":0.3728482022},
{"learn":[3.468134848],"iteration":732,"passed_time":1.019525813,"remaining_time":0.3713688843},
{"learn":[3.467820182],"iteration":733,"passed_time":1.020660785,"remaining_time":0.3698852435},
{"learn":[3.465776156],"iteration":734,"passed_time":1.0218684,"remaining_time":0.3684287429},
{"learn":[3.463037608],"iteration":735,"passed_time":1.023110453,"remaining_time":0.3669852712},
{"learn":[3.45965637],"iteration":736,"passed_time":1.024410049,"remaining_time":0.3655628803},
{"learn":[3.457275091],"iteration":737,"passed_time":1.025554085,"remaining_time":0.3640855966},
{"learn":[3.455522955],"iteration":738,"passed_time":1.026743311,"remaining_time":0.3626251748},
{"learn":[3.451270508],"iteration":739,"passed_time":1.028094565,"remaining_time":0.3612224148},
{"learn":[3.450978947],"iteration":740,"passed_time":1.02921038,"remaining_time":0.3597375012},
{"learn":[3.450608492],"iteration":741,"passed_time":1.030383502,"remaining_time":0.3582735088},
{"learn":[3.448122004],"iteration":742,"passed_time":1.031508071,"remaining_time":0.356793505},
{"learn":[3.445646714],"iteration":743,"passed_time":1.032713705,"remaining_time":0.3553423501},
{"learn":[3.44411263],"iteration":744,"passed_time":1.033865513,"remaining_time":0.3538734307},
{"learn":[3.443264164],"iteration":745,"passed_time":1.034981199,"remaining_time":0.3523930622},
{"learn":[3.439521363],"iteration":746,"passed_time":1.036644557,"remaining_time":0.3510991604},
{"learn":[3.436809225],"iteration":747,"passed_time":1.038423846,"remaining_time":0.3498433278},
{"learn":[3.435509465],"iteration":748,"passed_time":1.039694625,"remaining_time":0.3484156888},
{"learn":[3.434450277],"iteration":749,"passed_time":1.041108061,"remaining_time":0.3470360205},
{"learn":[3.431786753],"iteration":750,"passed_time":1.042562652,"remaining_time":0.3456699073},
{"learn":[3.430150302],"iteration":751,"passed_time":1.043997074,"remaining_time":0.3442969074},
{"learn":[3.42696281],"iteration":752,"passed_time":1.045828852,"remaining_time":0.3430540856},
{"learn":[3.426870334],"iteration":753,"passed_time":1.047313134,"remaining_time":0.3416963275},
{"learn":[3.425200309],"iteration":754,"passed_time":1.048687554,"remaining_time":0.3403025838},
{"learn":[3.423383783],"iteration":755,"passed_time":1.049953545,"remaining_time":0.3388738955},
{"learn":[3.422752979],"iteration":756,"passed_time":1.051027004,"remaining_time":0.3373838334},
{"learn":[3.420845924],"iteration":757,"passed_time":1.052372273,"remaining_time":0.335981649},
{"learn":[3.418917862],"iteration":758,"passed_time":1.053694777,"remaining_time":0.3345723862},
{"learn":[3.417095735],"iteration":759,"passed_time":1.054967094,"remaining_time":0.3331475035},
{"learn":[3.414391848],"iteration":760,"passed_time":1.056119043,"remaining_time":0.3316852184},
{"learn":[3.41426711],"iteration":761,"passed_time":1.057303109,"remaining_time":0.3302337794},
{"learn":[3.411976013],"iteration":762,"passed_time":1.058765347,"remaining_time":0.3288694459},
{"learn":[3.408614844],"iteration":763,"passed_time":1.060105639,"remaining_time":0.327467187},
{"learn":[3.407906721],"iteration":764,"passed_time":1.06130818,"remaining_time":0.3260227743},
{"learn":[3.407494015],"iteration":765,"passed_time":1.062536007,"remaining_time":0.3245867175},
{"learn":[3.406287128],"iteration":766,"passed_time":1.063690157,"remaining_time":0.3231288221},
{"learn":[3.404600442],"iteration":767,"passed_time":1.064855798,"remaining_time":0.321675189},
{"learn":[3.404012662],"iteration":768,"passed_time":1.066057999,"remaining_time":0.3202332871},
{"learn":[3.400398762],"iteration":769,"passed_time":1.067369768,"remaining_time":0.318824736},
{"learn":[3.399737714],"iteration":770,"passed_time":1.068675003,"remaining_time":0.317414495},
{"learn":[3.399185251],"iteration":771,"passed_time":1.070035607,"remaining_time":0.3160208787},
{"learn":[3.397245411],"iteration":772,"passed_time":1.07121453,"remaining_time":0.3145739953},
{"learn":[3.396229831],"iteration":773,"passed_time":1.072366795,"remaining_time":0.3131200202},
{"learn":[3.394002836],"iteration":774,"passed_time":1.073581502,"remaining_time":0.3116849521},
{"learn":[3.389617243],"iteration":775,"passed_time":1.074798832,"remaining_time":0.3102512092},
{"learn":[3.385426488],"iteration":776,"passed_time":1.075986125,"remaining_time":0.3088094026},
{"learn":[3.385072258],"iteration":777,"passed_time":1.077532584,"remaining_time":0.3074707373},
{"learn":[3.383842366],"iteration":778,"passed_time":1.079054952,"remaining_time":0.3061247039},
{"learn":[3.380110746],"iteration":779,"passed_time":1.08067433,"remaining_time":0.3048055802},
{"learn":[3.378595218],"iteration":780,"passed_time":1.081873712,"remaining_time":0.3033679166},
{"learn":[3.377371219],"iteration":781,"passed_time":1.083035573,"remaining_time":0.3019204026},
{"learn":[3.375814782],"iteration":782,"passed_time":1.084221616,"remaining_time":0.3004803202},
{"learn":[3.374195887],"iteration":783,"passed_time":1.085372399,"remaining_time":0.2990311712},
{"learn":[3.373704309],"iteration":784,"passed_time":1.086618552,"remaining_time":0.2976089028},
{"learn":[3.372971757],"iteration":785,"passed_time":1.087830456,"remaining_time":0.2961777578},
{"learn":[3.371565136],"iteration":786,"passed_time":1.089128641,"remaining_time":0.2947705216},
{"learn":[3.3700309],"iteration":787,"passed_time":1.090233091,"remaining_time":0.2933114407},
{"learn":[3.368186663],"iteration":788,"passed_time":1.091329244,"remaining_time":0.29185104},
{"learn":[3.366710398],"iteration":789,"passed_time":1.092422573,"remaining_time":0.2903908106},
{"learn":[3.364598042],"iteration":790,"passed_time":1.093426612,"remaining_time":0.2889079164},
{"learn":[3.36348442],"iteration":791,"passed_time":1.094521691,"remaining_time":0.287450141},
{"learn":[3.362001759],"iteration":792,"passed_time":1.095674805,"remaining_time":0.2860084296},
{"learn":[3.361580401],"iteration":793,"passed_time":1.096752911,"remaining_time":0.2845479845},
{"learn":[3.359543675],"iteration":794,"passed_time":1.097883801,"remaining_time":0.2831021121},
{"learn":[3.35766119],"iteration":795,"passed_time":1.098943563,"remaining_time":0.2816388026},
{"learn":[3.354592969],"iteration":796,"passed_time":1.100208713,"remaining_time":0.2802288189},
{"learn":[3.350985986],"iteration":797,"passed_time":1.101269462,"remaining_time":0.2787674578},
{"learn":[3.349589624],"iteration":798,"passed_time":1.102451356,"remaining_time":0.2773375752},
{"learn":[3.349110856],"iteration":799,"passed_time":1.103551685,"remaining_time":0.2758879214},
{"learn":[3.345315441],"iteration":800,"passed_time":1.104642952,"remaining_time":0.2744368882},
{"learn":[3.34397474],"iteration":801,"passed_time":1.105782973,"remaining_time":0.2729987889},
{"learn":[3.343800902],"iteration":802,"passed_time":1.106803662,"remaining_time":0.2715321563},
{"learn":[3.342329465],"iteration":803,"passed_time":1.107870434,"remaining_time":0.2700778671},
{"learn":[3.34220347],"iteration":804,"passed_time":1.10888551,"remaining_time":0.2686120179},
{"learn":[3.341279219],"iteration":805,"passed_time":1.110060401,"remaining_time":0.2671857541},
{"learn":[3.337329521],"iteration":806,"passed_time":1.111130714,"remaining_time":0.2657351026},
{"learn":[3.336708453],"iteration":807,"passed_time":1.112243224,"remaining_time":0.2642954195},
{"learn":[3.333252703],"iteration":808,"passed_time":1.113360494,"remaining_time":0.2628576693},
{"learn":[3.332186769],"iteration":809,"passed_time":1.114513313,"remaining_time":0.2614290488},
{"learn":[3.330594851],"iteration":810,"passed_time":1.115588729,"remaining_time":0.2599830701},
{"learn":[3.327867442],"iteration":811,"passed_time":1.116727483,"remaining_time":0.2585526684},
{"learn":[3.327563111],"iteration":812,"passed_time":1.117756425,"remaining_time":0.2570977263},
{"learn":[3.326308994],"iteration":813,"passed_time":1.11882974,"remaining_time":0.2556539702},
{"learn":[3.326249879],"iteration":814,"passed_time":1.11984711,"remaining_time":0.2541984237},
{"learn":[3.322336238],"iteration":815,"passed_time":1.120920451,"remaining_time":0.2527565723},
{"learn":[3.320491154],"iteration":816,"passed_time":1.122002807,"remaining_time":0.2513176422},
{"learn":[3.320434271],"iteration":817,"passed_time":1.12298358,"remaining_time":0.2498569824},
{"learn":[3.319609638],"iteration":818,"passed_time":1.124002931,"remaining_time":0.2484060201},
{"learn":[3.316182682],"iteration":819,"passed_time":1.125099188,"remaining_time":0.2469729925},
{"learn":[3.313126612],"iteration":820,"passed_time":1.126182906,"remaining_time":0.2455380514},
{"learn":[3.311222803],"iteration":821,"passed_time":1.127320884,"remaining_time":0.2441157145},
{"learn":[3.309627335],"iteration":822,"passed_time":1.128522999,"remaining_time":0.2427078625},
{"learn":[3.307974895],"iteration":823,"passed_time":1.12982007,"remaining_time":0.2413207917},
{"learn":[3.307321505],"iteration":824,"passed_time":1.131002912,"remaining_time":0.2399097087},
{"learn":[3.306759087],"iteration":825,"passed_time":1.13217188,"remaining_time":0.2384962555},
{"learn":[3.30484037],"iteration":826,"passed_time":1.133348182,"remaining_time":0.2370849281},
{"learn":[3.30201994],"iteration":827,"passed_time":1.134429455,"remaining_time":0.2356544278},
{"learn":[3.299302297],"iteration":828,"passed_time":1.135564073,"remaining_time":0.2342357739},
{"learn":[3.298132671],"iteration":829,"passed_time":1.136600522,"remaining_time":0.2327976973},
{"learn":[3.296976183],"iteration":830,"passed_time":1.137718313,"remaining_time":0.2313771298},
{"learn":[3.293144745],"iteration":831,"passed_time":1.138858022,"remaining_time":0.2299617159},
{"learn":[3.290284404],"iteration":832,"passed_time":1.139957018,"remaining_time":0.228538802},
{"learn":[3.288285745],"iteration":833,"passed_time":1.141060494,"remaining_time":0.2271175564},
{"learn":[3.286662667],"iteration":834,"passed_time":1.142220697,"remaining_time":0.2257082814},
{"learn":[3.285692682],"iteration":835,"passed_time":1.143339893,"remaining_time":0.224291558},
{"learn":[3.284565611],"iteration":836,"passed_time":1.144471902,"remaining_time":0.2228780407},
{"learn":[3.283897383],"iteration":837,"passed_time":1.145727327,"remaining_time":0.2214890538},
{"learn":[3.280712855],"iteration":838,"passed_time":1.146897594,"remaining_time":0.2200840438},
{"learn":[3.280468341],"iteration":839,"passed_time":1.147894091,"remaining_time":0.2186464935},
{"learn":[3.277814895],"iteration":840,"passed_time":1.148963842,"remaining_time":0.2172238417},
{"learn":[3.276316385],"iteration":841,"passed_time":1.150106628,"remaining_time":0.215815733},
{"learn":[3.27557063],"iteration":842,"passed_time":1.151346705,"remaining_time":0.2144263733},
{"learn":[3.27499628],"iteration":843,"passed_time":1.152481548,"remaining_time":0.2130179164},
{"learn":[3.273569958],"iteration":844,"passed_time":1.153491869,"remaining_time":0.2115872659},
{"learn":[3.269665595],"iteration":845,"passed_time":1.154671222,"remaining_time":0.2101883784},
{"learn":[3.267984685],"iteration":846,"passed_time":1.155762788,"remaining_time":0.2087741517},
{"learn":[3.267702508],"iteration":847,"passed_time":1.156808445,"remaining_time":0.2073524572},
{"learn":[3.266671924],"iteration":848,"passed_time":1.157884264,"remaining_time":0.2059370128},
{"learn":[3.265359825],"iteration":849,"passed_time":1.159007583,"remaining_time":0.2045307499},
{"learn":[3.2618983],"iteration":850,"passed_time":1.160065458,"remaining_time":0.2031136936},
{"learn":[3.260456253],"iteration":851,"passed_time":1.161019594,"remaining_time":0.2016794601},
{"learn":[3.258389147],"iteration":852,"passed_time":1.162185166,"remaining_time":0.2002827895},
{"learn":[3.258108469],"iteration":853,"passed_time":1.163667243,"remaining_time":0.1989407698},
{"learn":[3.256424936],"iteration":854,"passed_time":1.164837718,"remaining_time":0.1975455778},
{"learn":[3.254817983],"iteration":855,"passed_time":1.166003065,"remaining_time":0.1961500483},
{"learn":[3.253898449],"iteration":856,"passed_time":1.167067126,"remaining_time":0.1947381553},
{"learn":[3.253023652],"iteration":857,"passed_time":1.16810544,"remaining_time":0.1933228117},
{"learn":[3.252845542],"iteration":858,"passed_time":1.169156562,"remaining_time":0.1919104485},
{"learn":[3.252316026],"iteration":859,"passed_time":1.170109618,"remaining_time":0.1904829612},
{"learn":[3.24975301],"iteration":860,"passed_time":1.171152123,"remaining_time":0.1890710164},
{"learn":[3.249151075],"iteration":861,"passed_time":1.172096948,"remaining_time":0.187644291},
{"learn":[3.246257135],"iteration":862,"passed_time":1.173136554,"remaining_time":0.1862337288},
{"learn":[3.243826471],"iteration":863,"passed_time":1.174405004,"remaining_time":0.1848600469},
{"learn":[3.243190653],"iteration":864,"passed_time":1.17549936,"remaining_time":0.1834594377},
{"learn":[3.24008797],"iteration":865,"passed_time":1.176690942,"remaining_time":0.18207458},
{"learn":[3.240036811],"iteration":866,"passed_time":1.177684527,"remaining_time":0.1806597948},
{"learn":[3.238676314],"iteration":867,"passed_time":1.178888433,"remaining_time":0.1792779644},
{"learn":[3.237848782],"iteration":868,"passed_time":1.180131514,"remaining_time":0.1779024491},
{"learn":[3.236405498],"iteration":869,"passed_time":1.181223703,"remaining_time":0.1765046913},
{"learn":[3.233378068],"iteration":870,"passed_time":1.182562754,"remaining_time":0.1751441966},
{"learn":[3.233169169],"iteration":871,"passed_time":1.183786296,"remaining_time":0.1737667958},
{"learn":[3.232434885],"iteration":872,"passed_time":1.184967575,"remaining_time":0.1723835991},
{"learn":[3.229978115],"iteration":873,"passed_time":1.186135358,"remaining_time":0.1709989188},
{"learn":[3.229648848],"iteration":874,"passed_time":1.187288634,"remaining_time":0.169612662},
{"learn":[3.227208761],"iteration":875,"passed_time":1.188419846,"remaining_time":0.1682238138},
{"learn":[3.226258869],"iteration":876,"passed_time":1.189434408,"remaining_time":0.1668191929},
{"learn":[3.225331995],"iteration":877,"passed_time":1.190544646,"remaining_time":0.1654287549},
{"learn":[3.221968268],"iteration":878,"passed_time":1.191670244,"remaining_time":0.1640410689},
{"learn":[3.221166317],"iteration":879,"passed_time":1.192749324,"remaining_time":0.1626476351},
{"learn":[3.220047503],"iteration":880,"passed_time":1.193716699,"remaining_time":0.1612398265},
{"learn":[3.21982781],"iteration":881,"passed_time":1.194712711,"remaining_time":0.159836848},
{"learn":[3.216693405],"iteration":882,"passed_time":1.195792461,"remaining_time":0.1584458866},
{"learn":[3.214798761],"iteration":883,"passed_time":1.196856819,"remaining_time":0.1570536097},
{"learn":[3.214395085],"iteration":884,"passed_time":1.197932234,"remaining_time":0.1556635106},
{"learn":[3.213470696],"iteration":885,"passed_time":1.199056509,"remaining_time":0.1542804086},
{"learn":[3.211595017],"iteration":886,"passed_time":1.200121477,"remaining_time":0.1528903347},
{"learn":[3.210965255],"iteration":887,"passed_time":1.201234091,"remaining_time":0.1515070024},
{"learn":[3.209413583],"iteration":888,"passed_time":1.202469857,"remaining_time":0.1501396559},
{"learn":[3.208331683],"iteration":889,"passed_time":1.203563337,"remaining_time":0.1487550191},
{"learn":[3.207110711],"iteration":890,"passed_time":1.204721289,"remaining_time":0.1473789231},
{"learn":[3.204519413],"iteration":891,"passed_time":1.205931567,"remaining_time":0.1460096516},
{"learn":[3.201421296],"iteration":892,"passed_time":1.20704639,"remaining_time":0.1446292987},
{"learn":[3.200691259],"iteration":893,"passed_time":1.208357899,"remaining_time":0.1432728605},
{"learn":[3.200485067],"iteration":894,"passed_time":1.209440993,"remaining_time":0.1418897255},
{"learn":[3.197467568],"iteration":895,"passed_time":1.210556577,"remaining_time":0.1405110313},
{"learn":[3.195838544],"iteration":896,"passed_time":1.211565587,"remaining_time":0.1391206862},
{"learn":[3.195671746],"iteration":897,"passed_time":1.212557919,"remaining_time":0.137729296},
{"learn":[3.194213094],"iteration":898,"passed_time":1.21359798,"remaining_time":0.1363441557},
{"learn":[3.192884691],"iteration":899,"passed_time":1.214666219,"remaining_time":0.1349629132},
{"learn":[3.188364239],"iteration":900,"passed_time":1.215822787,"remaining_time":0.133592071},
{"learn":[3.185219478],"iteration":901,"passed_time":1.216881523,"remaining_time":0.1322110745},
{"learn":[3.184120387],"iteration":902,"passed_time":1.217986371,"remaining_time":0.1308357453},
{"learn":[3.183725321],"iteration":903,"passed_time":1.219071036,"remaining_time":0.1294588711},
{"learn":[3.181264554],"iteration":904,"passed_time":1.220279362,"remaining_time":0.1280956236},
{"learn":[3.180741589],"iteration":905,"passed_time":1.221453253,"remaining_time":0.1267291455},
{"learn":[3.179782639],"iteration":906,"passed_time":1.222563256,"remaining_time":0.1253565411},
{"learn":[3.176377564],"iteration":907,"passed_time":1.223570347,"remaining_time":0.123974088},
{"learn":[3.174078182],"iteration":908,"passed_time":1.224514694,"remaining_time":0.1225861795},
{"learn":[3.171242379],"iteration":909,"passed_time":1.225560384,"remaining_time":0.1212092688},
{"learn":[3.170421012],"iteration":910,"passed_time":1.226653646,"remaining_time":0.1198377327},
{"learn":[3.170087224],"iteration":911,"passed_time":1.227757225,"remaining_time":0.1184678024},
{"learn":[3.167303059],"iteration":912,"passed_time":1.228737019,"remaining_time":0.1170866601},
{"learn":[3.16705966],"iteration":913,"passed_time":1.229694814,"remaining_time":0.1157043261},
{"learn":[3.165667683],"iteration":914,"passed_time":1.230734533,"remaining_time":0.1143305304},
{"learn":[3.164689733],"iteration":915,"passed_time":1.231784953,"remaining_time":0.1129584455},
{"learn":[3.163311455],"iteration":916,"passed_time":1.232838921,"remaining_time":0.1115873832},
{"learn":[3.159425016],"iteration":917,"passed_time":1.234028918,"remaining_time":0.1102291626},
{"learn":[3.159327058],"iteration":918,"passed_time":1.235006157,"remaining_time":0.1088525558},
{"learn":[3.15819426],"iteration":919,"passed_time":1.236044466,"remaining_time":0.1074821275},
{"learn":[3.157086603],"iteration":920,"passed_time":1.237108203,"remaining_time":0.1061146016},
{"learn":[3.153354154],"iteration":921,"passed_time":1.238100361,"remaining_time":0.1047416791},
{"learn":[3.153261317],"iteration":922,"passed_time":1.239121508,"remaining_time":0.1033720001},
{"learn":[3.153168454],"iteration":923,"passed_time":1.240150833,"remaining_time":0.1020037482},
{"learn":[3.152080399],"iteration":924,"passed_time":1.241190053,"remaining_time":0.1006370313},
{"learn":[3.151635144],"iteration":925,"passed_time":1.242332158,"remaining_time":0.09927924371},
{"learn":[3.147762655],"iteration":926,"passed_time":1.243445356,"remaining_time":0.09791964508},
{"learn":[3.147172317],"iteration":927,"passed_time":1.244464571,"remaining_time":0.09655328567},
{"learn":[3.146254125],"iteration":928,"passed_time":1.245565979,"remaining_time":0.09519395536},
{"learn":[3.144869828],"iteration":929,"passed_time":1.24667384,"remaining_time":0.09383566536},
{"learn":[3.143466218],"iteration":930,"passed_time":1.247791038,"remaining_time":0.09247860543},
{"learn":[3.141919643],"iteration":931,"passed_time":1.248934589,"remaining_time":0.09112398288},
{"learn":[3.141054135],"iteration":932,"passed_time":1.250055917,"remaining_time":0.08976821699},
{"learn":[3.139390417],"iteration":933,"passed_time":1.251176886,"remaining_time":0.08841292768},
{"learn":[3.139025283],"iteration":934,"passed_time":1.252348632,"remaining_time":0.08706166959},
{"learn":[3.137824183],"iteration":935,"passed_time":1.253442379,"remaining_time":0.08570546183},
{"learn":[3.135620453],"iteration":936,"passed_time":1.254609652,"remaining_time":0.0843547578},
{"learn":[3.13443178],"iteration":937,"passed_time":1.255766189,"remaining_time":0.0830037353},
{"learn":[3.132765713],"iteration":938,"passed_time":1.256887557,"remaining_time":0.08165084236},
{"learn":[3.131434124],"iteration":939,"passed_time":1.2579275,"remaining_time":0.08029324467},
{"learn":[3.128384262],"iteration":940,"passed_time":1.259006236,"remaining_time":0.07893875446},
{"learn":[3.128120455],"iteration":941,"passed_time":1.26002617,"remaining_time":0.07758122917},
{"learn":[3.126314615],"iteration":942,"passed_time":1.261177564,"remaining_time":0.07623236604},
{"learn":[3.125409666],"iteration":943,"passed_time":1.262295829,"remaining_time":0.07488195598},
{"learn":[3.123072589],"iteration":944,"passed_time":1.263566839,"remaining_time":0.07354092712},
{"learn":[3.122921099],"iteration":945,"passed_time":1.264632478,"remaining_time":0.07218832328},
{"learn":[3.122182662],"iteration":946,"passed_time":1.265733075,"remaining_time":0.07083828194},
{"learn":[3.120040951],"iteration":947,"passed_time":1.26687531,"remaining_time":0.06949105076},
{"learn":[3.118767799],"iteration":948,"passed_time":1.267930822,"remaining_time":0.06813959108},
{"learn":[3.118203218],"iteration":949,"passed_time":1.268977087,"remaining_time":0.06678826774},
{"learn":[3.116343362],"iteration":950,"passed_time":1.270208576,"remaining_time":0.06544712957},
{"learn":[3.11480829],"iteration":951,"passed_time":1.27149694,"remaining_time":0.0641090894},
{"learn":[3.112607903],"iteration":952,"passed_time":1.27252439,"remaining_time":0.06275828577},
{"learn":[3.111661241],"iteration":953,"passed_time":1.273519125,"remaining_time":0.06140658257},
{"learn":[3.110249676],"iteration":954,"passed_time":1.274538206,"remaining_time":0.0600567741},
{"learn":[3.107333579],"iteration":955,"passed_time":1.275494481,"remaining_time":0.05870476691},
{"learn":[3.107149851],"iteration":956,"passed_time":1.276484556,"remaining_time":0.05735510545},
{"learn":[3.106867336],"iteration":957,"passed_time":1.277512823,"remaining_time":0.05600786905},
{"learn":[3.10364681],"iteration":958,"passed_time":1.278631966,"remaining_time":0.05466518309},
{"learn":[3.102703811],"iteration":959,"passed_time":1.279832287,"remaining_time":0.05332634529},
{"learn":[3.101469264],"iteration":960,"passed_time":1.280847016,"remaining_time":0.05198026393},
{"learn":[3.09863569],"iteration":961,"passed_time":1.282062807,"remaining_time":0.05064281358},
{"learn":[3.09645939],"iteration":962,"passed_time":1.283209383,"remaining_time":0.04930295655},
{"learn":[3.096240186],"iteration":963,"passed_time":1.284228503,"remaining_time":0.04795874077},
{"learn":[3.094838828],"iteration":964,"passed_time":1.28534581,"remaining_time":0.04661875996},
{"learn":[3.094176802],"iteration":965,"passed_time":1.286345224,"remaining_time":0.0452750907},
{"learn":[3.093182279],"iteration":966,"passed_time":1.287333751,"remaining_time":0.04393176193},
{"learn":[3.090150687],"iteration":967,"passed_time":1.288374643,"remaining_time":0.04259089727},
{"learn":[3.088612829],"iteration":968,"passed_time":1.289393051,"remaining_time":0.0412499325},
{"learn":[3.087153684],"iteration":969,"passed_time":1.290455079,"remaining_time":0.03991098182},
{"learn":[3.085866843],"iteration":970,"passed_time":1.291535118,"remaining_time":0.03857313948},
{"learn":[3.082669094],"iteration":971,"passed_time":1.292701895,"remaining_time":0.0372383262},
{"learn":[3.081047548],"iteration":972,"passed_time":1.293876497,"remaining_time":0.03590407546},
{"learn":[3.079684322],"iteration":973,"passed_time":1.295082825,"remaining_time":0.03457099944},
{"learn":[3.07613431],"iteration":974,"passed_time":1.296332328,"remaining_time":0.03323929047},
{"learn":[3.074005935],"iteration":975,"passed_time":1.297465713,"remaining_time":0.03190489459},
{"learn":[3.072988853],"iteration":976,"passed_time":1.298636548,"remaining_time":0.03057179181},
{"learn":[3.072344268],"iteration":977,"passed_time":1.299687575,"remaining_time":0.02923632581},
{"learn":[3.070654438],"iteration":978,"passed_time":1.300860255,"remaining_time":0.02790405041},
{"learn":[3.069724506],"iteration":979,"passed_time":1.302054187,"remaining_time":0.02657253442},
{"learn":[3.067763166],"iteration":980,"passed_time":1.303244239,"remaining_time":0.02524122379},
{"learn":[3.066737893],"iteration":981,"passed_time":1.304381446,"remaining_time":0.02390923221},
{"learn":[3.065248174],"iteration":982,"passed_time":1.305490099,"remaining_time":0.02257714311},
{"learn":[3.063186837],"iteration":983,"passed_time":1.306692766,"remaining_time":0.02124703685},
{"learn":[3.062880371],"iteration":984,"passed_time":1.308115226,"remaining_time":0.01992053643},
{"learn":[3.061288645],"iteration":985,"passed_time":1.309252592,"remaining_time":0.0185897934},
{"learn":[3.059970575],"iteration":986,"passed_time":1.310590904,"remaining_time":0.0172620889},
{"learn":[3.059576341],"iteration":987,"passed_time":1.311889768,"remaining_time":0.01593388382},
{"learn":[3.058175919],"iteration":988,"passed_time":1.313127711,"remaining_time":0.01460506048},
{"learn":[3.056830702],"iteration":989,"passed_time":1.314129016,"remaining_time":0.01327403047},
{"learn":[3.056336579],"iteration":990,"passed_time":1.315244291,"remaining_time":0.01194470093},
{"learn":[3.055810414],"iteration":991,"passed_time":1.316285933,"remaining_time":0.01061520914},
{"learn":[3.055476518],"iteration":992,"passed_time":1.317347872,"remaining_time":0.009286440186},
{"learn":[3.053331734],"iteration":993,"passed_time":1.318435224,"remaining_time":0.007958361511},
{"learn":[3.050890374],"iteration":994,"passed_time":1.319434556,"remaining_time":0.0066303244},
{"learn":[3.04972623],"iteration":995,"passed_time":1.320590416,"remaining_time":0.005303575966},
{"learn":[3.047217327],"iteration":996,"passed_time":1.321742107,"remaining_time":0.003977157794},
{"learn":[3.047155483],"iteration":997,"passed_time":1.32280556,"remaining_time":0.002650912945},
{"learn":[3.04430671],"iteration":998,"passed_time":1.323968617,"remaining_time":0.001325293911},
{"learn":[3.042664195],"iteration":999,"passed_time":1.325234477,"remaining_time":0}
]}